Workbook
Name ProductsList: Lists!$A$2:$A$8
Name PacksList: Lists!$B$2:$B$4
Name QualityList: Lists!$C$2:$C$5
Name ApprovalList: Lists!$D$2:$D$4
Name CustTypeList: Lists!$E$2:$E$6
Name ABCList: Lists!$F$2:$F$4
Name CustStatusList: Lists!$G$2:$G$4
Name ExpenseList: Lists!$H$2:$H$11
Name PayList: Lists!$I$2:$I$5
Name CityList: Lists!$J$2:$J$9
Name LocList: Lists!$K$2:$K$5
Name InvKindList: Lists!$L$2:$L$3
Name UnitList: Lists!$M$2:$M$3
Name RoleList: Lists!$N$2:$N$7
Name EmpStatusList: Lists!$O$2:$O$3
Name RegionList: Lists!$P$2:$P$7
Name StaffList: Lists!$R$2:$R$21
Name SupplierNames: Suppliers!$A$2:$A$151
Name CustomerNames: Customers!$A$2:$A$151
Name CurrentYear: تنظیمات!$B$2
Name CurrentMonth: تنظیمات!$B$3
Name TodayShamsi: تنظیمات!$B$4

Sheet راهنما
A1: راهنمای استفاده — کارگاه بسته‌بندی حبوبات پلدختر
A2: هدف: مدیر در کمتر از ۱۰ دقیقه بفهمد چه چیزی خوب است، چه چیزی مشکل دارد، و کجا باید دخالت کند.
A4: ۱) هر کس چه چیزی را وارد می‌کند
A5: شخص | B5: وظیفه در کارگاه | C5: برگه Excel | D5: فرم کاغذی | E5: چه چیزی را می‌نویسد | F5: چه چیزی را دست نزند
A6: مدیر / مالک | B6: خرید، فروش، مالی، تصمیم | C6: Purchases + تنظیمات + Dashboard | D6: تأیید خرید و هزینه | E6: تأیید بار، اهداف KPI، نگاه داشبورد | F6: ردیف‌های فرمول خاکستری
A7: پدر مدیر | B7: انبار و کمک تولید | C7: Inventory + کمک Production | D7: شمارش موجودی، دریافت مواد | E7: شمارش و تعدیل انبار | F7: خرید و فروش (تکراری نشود)
A8: نیروی خانم | B8: پاک‌کنی و بسته‌بندی | C8: Production (یا فقط فرم کاغذی) | D8: گزارش تولید روزانه | E8: مقدار ورودی، پاک‌شده، وزن بسته | F8: درصد ضایعات (خودکار است)
A9: ویزیتور آقا | B9: ویزیت، فروش، پخش | C9: Sales + SalesRep + Customers | D9: گزارش ویزیت، خروج کالا، تحویل پخش | E9: سفارش، وصول، مسیر، کیلومتر | F9: مانده حساب (خودکار است)
A11: ۲) روال روزانه مدیر (زیر ۱۰ دقیقه)
A12: ۱. در برگه تنظیمات، «تاریخ امروز» و اگر ماه عوض شده «ماه جاری» را به‌روز کنید.
A13: ۲. فرم‌های کاغذی دیروز را از روی میز جمع کنید و به مسئول مربوطه بدهید تا در Excel بزند (یا خودتان).
A14: ۳. برگه Dashboard را باز کنید. نوار بالای جدول را بخوانید.
A15: ۴. اگر همه چیز مطلوب است، صفحه را ببندید. نیازی به خواندن فرم‌ها نیست.
A16: ۵. اگر زرد است: تا پایان هفته صبر و نظارت. اگر قرمز است: متن «اقدام اصلاحی» همان ردیف را همان روز اجرا کنید.
A17: ۶. چرخه: ثبت → KPI → داشبورد → تشخیص انحراف → اقدام → بهبود هدف در تنظیمات اگر لازم شد.
A19: ۳) قوانین مهم
A20: تاریخ را همیشه با اعداد انگلیسی و صفر جلو ماه/روز بنویسید: 1405/06/18 نه ۱۴۰۵/۶/۱۸.
A21: سلول کرم‌رنگ = ورود اطلاعات. سلول خاکستری = فرمول. فرمول را پاک نکنید. اگر لازم شد از Review برگه را Unprotect کنید (رمز ندارد).
A22: هر داده فقط یک بار وارد می‌شود. خرید در Purchases، تولید در Production، فروش در Sales. موجودی خودش حساب می‌شود.
A23: فقط بار «تأیید شده» وارد موجودی و هزینه خرید می‌شود. بار ضعیف را «رد شده» بزنید.
... A31: ۴) فهرست برگه‌ها
A32: برگه | B32: کاربرد | C32: چه کسی | D32: ورود یا خواندنی
A33: راهنما | B33: همین صفحه | C33: همه | D33: خواندنی
A34: Dashboard | B34: وضعیت کارگاه در یک نگاه | C34: مدیر | D34: خواندنی — خودکار
A35: تنظیمات | B35: سال/ماه/امروز و اهداف KPI | C35: مدیر | D35: ورود اهداف
A36: Purchases | B36: خرید مواد اولیه | C36: مدیر | D36: ورود
A37: Inventory | B37: موجودی لحظه‌ای + تعدیل | C37: پدر / مدیر | D37: عمدتاً خودکار
A38: Production | B38: تولید و ضایعات | C38: بسته‌بندی / پدر | D38: ورود
A39: Sales | B39: فاکتور فروش و وصول | C39: ویزیتور / مدیر | D39: ورود
A40: Customers | B40: دفتر مشتری و ABC | C40: ویزیتور / مدیر | D40: ورود مشخصات
A41: SalesRep | B41: عملکرد روزانه ویزیتور | C41: ویزیتور | D41: ورود
A42: Expenses | B42: هزینه‌ها | C42: مدیر / پدر | D42: ورود
A43: Suppliers | B43: بانک تأمین‌کننده و امتیاز | C43: مدیر | D43: ورود
... A46: فرم‌ها | B46: ۸ فرم A4 قابل چاپ | C46: کارگران | D46: چاپ؛ با خودکار پر می‌شود
A48: ۵) داده نمونه
A49: این فایل با داده نمونه شهریور ۱۴۰۵ پر شده تا داشبورد خالی نباشد و چراغ‌ها دیده شوند. قبل از استفاده واقعی: ردیف‌های نمونه را پاک کنید (محتوای سلول‌های کرم را خالی کنید، فرمول خاکستری را نزنید) یا یک کپی از فایل بگیرید و روی کپی کار کنید. ردیف «موجودی اول دوره» در تأمین‌کنندگان را نگه دارید یا موجودی واقعی را جایگزین کنید.

Sheet Dashboard
A1: =تنظیمات!B8
A2: =CONCATENATE("داشبورد مدیریتی | ","سال ",تنظیمات!B2," — ماه ",تنظیمات!D2," | تاریخ امروز: ",تنظیمات!F2," | اگر چراغی قرمز نیست، دخالت لازم نیست")
A3: =IF(COUNTIF(E7:E22,"بحرانی")>0,CONCATENATE(COUNTIF(E7:E22,"بحرانی")," شاخص بحرانی — امروز اقدام کنید"),IF(COUNTIF(E7:E22,"نیاز به بررسی")>0,CONCATENATE(COUNTIF(E7:E22,"نیاز به بررسی")," شاخص نیاز به بررسی دارد"),"همه شاخص‌های مهم مطلوب‌اند. کارگاه روی روال است."))
A5: شاخص | B5: مقدار | C5: واحد | D5: هدف | E5: وضعیت | F5: اقدام اصلاحی
A7: فروش روزانه | B7: =SUMIF(Sales!$B$4:$B$151,تنظیمات!$F$2,Sales!$L$4:$L$151) | C7: تومان | D7: =تنظیمات!C18 | E7: =IF(B7="","—",IF(B7>=D7,"مطلوب",IF(B7>=تنظیمات!D18,"نیاز به بررسی","بحرانی"))) | F7: =IF(E7="بحرانی",تنظیمات!G18,IF(E7="نیاز به بررسی","زیر نظر بگیرید — اگر تا پایان هفته سبز نشد اقدام کنید",IF(E7="مطلوب","","")))
A8: فروش ماهانه | B8: =SUMIFS(Sales!$L$4:$L$151,Sales!$P$4:$P$151,تنظیمات!$B$2,Sales!$Q$4:$Q$151,تنظیمات!$D$2) | C8: تومان | D8: =تنظیمات!C19 | E8: =IF(B8="","—",IF(B8>=D8,"مطلوب",IF(B8>=تنظیمات!D19,"نیاز به بررسی","بحرانی"))) | F8: =IF(E8="بحرانی",تنظیمات!G19,IF(E8="نیاز به بررسی","زیر نظر بگیرید — اگر تا پایان هفته سبز نشد اقدام کنید",IF(E8="مطلوب","","")))
A9: سود ناخالص | B9: =(SUMIFS(Sales!$L$4:$L$151,Sales!$P$4:$P$151,تنظیمات!$B$2,Sales!$Q$4:$Q$151,تنظیمات!$D$2))-(SUMIFS(Purchases!$G$4:$G$151,Purchases!$M$4:$M$151,تنظیمات!$B$2,Purchases!$N$4:$N$151,تنظیمات!$D$2,Purchases!$K$4:$K$151,"تأیید شده")+SUMIFS(Purchases!$H$4:$H$151,Purchases!$M$4:$M$151,تنظیمات!$B$2,Purchases!$N$4:$N$151,تنظیمات!$D$2,Purchases!$K$4:$K$151,"تأیید شده"))-(SUMIFS(Expenses!$D$4:$D$151,Expenses!$H$4:$H$151,تنظیمات!$B$2,Expenses!$I$4:$I$151,تنظیمات!$D$2)) | C9: تومان | D9: =تنظیمات!C20 | E9: =IF(B9="","—",IF(B9>=D9,"مطلوب",IF(B9>=تنظیمات!D20,"نیاز به بررسی","بحرانی"))) | F9: =IF(E9="بحرانی",تنظیمات!G20,IF(E9="نیاز به بررسی","زیر نظر بگیرید — اگر تا پایان هفته سبز نشد اقدام کنید",IF(E9="مطلوب","","")))
A10: خرید مواد اولیه | B10: =SUMIFS(Purchases!$G$4:$G$151,Purchases!$M$4:$M$151,تنظیمات!$B$2,Purchases!$N$4:$N$151,تنظیمات!$D$2,Purchases!$K$4:$K$151,"تأیید شده")+SUMIFS(Purchases!$H$4:$H$151,Purchases!$M$4:$M$151,تنظیمات!$B$2,Purchases!$N$4:$N$151,تنظیمات!$D$2,Purchases!$K$4:$K$151,"تأیید شده") | C10: تومان | D10: — | E10: ="—" | F10: =""
A11: موجودی مواد اولیه | B11: =Inventory!C21 | C11: کیلوگرم | D11: =تنظیمات!C22 | E11: =IF(B11="","—",IF(B11>=D11,"مطلوب",IF(B11>=تنظیمات!D22,"نیاز به بررسی","بحرانی"))) | F11: =IF(E11="بحرانی",تنظیمات!G22,IF(E11="نیاز به بررسی","زیر نظر بگیرید — اگر تا پایان هفته سبز نشد اقدام کنید",IF(E11="مطلوب","","")))
A12: موجودی محصول نهایی | B12: =Inventory!C22 | C12: کیلوگرم | D12: =تنظیمات!C23 | E12: =IF(B12="","—",IF(B12>=D12,"مطلوب",IF(B12>=تنظیمات!D23,"نیاز به بررسی","بحرانی"))) | F12: =IF(E12="بحرانی",تنظیمات!G23,IF(E12="نیاز به بررسی","زیر نظر بگیرید — اگر تا پایان هفته سبز نشد اقدام کنید",IF(E12="مطلوب","","")))
A13: مقدار تولید | B13: =SUMIFS(Production!$E$4:$E$151,Production!$M$4:$M$151,تنظیمات!$B$2,Production!$N$4:$N$151,تنظیمات!$D$2) | C13: کیلوگرم | D13: =تنظیمات!C24 | E13: =IF(B13="","—",IF(B13>=D13,"مطلوب",IF(B13>=تنظیمات!D24,"نیاز به بررسی","بحرانی"))) | F13: =IF(E13="بحرانی",تنظیمات!G24,IF(E13="نیاز به بررسی","زیر نظر بگیرید — اگر تا پایان هفته سبز نشد اقدام کنید",IF(E13="مطلوب","","")))
A14: درصد ضایعات | B14: =IFERROR(SUMIFS(Production!$F$4:$F$151,Production!$M$4:$M$151,تنظیمات!$B$2,Production!$N$4:$N$151,تنظیمات!$D$2)/SUMIFS(Production!$D$4:$D$151,Production!$M$4:$M$151,تنظیمات!$B$2,Production!$N$4:$N$151,تنظیمات!$D$2),0) | C14: درصد | D14: =تنظیمات!C25 | E14: =IF(B14="","—",IF(B14<=D14,"مطلوب",IF(B14<=تنظیمات!D25,"نیاز به بررسی","بحرانی"))) | F14: =IF(E14="بحرانی",تنظیمات!G25,IF(E14="نیاز به بررسی","زیر نظر بگیرید — اگر تا پایان هفته سبز نشد اقدام کنید",IF(E14="مطلوب","","")))
A15: تعداد سفارش‌ها | B15: =COUNTIFS(Sales!$P$4:$P$151,تنظیمات!$B$2,Sales!$Q$4:$Q$151,تنظیمات!$D$2,Sales!$B$4:$B$151,"<>") | C15: عدد | D15: =تنظیمات!C26 | E15: =IF(B15="","—",IF(B15>=D15,"مطلوب",IF(B15>=تنظیمات!D26,"نیاز به بررسی","بحرانی"))) | F15: =IF(E15="بحرانی",تنظیمات!G26,IF(E15="نیاز به بررسی","زیر نظر بگیرید — اگر تا پایان هفته سبز نشد اقدام کنید",IF(E15="مطلوب","","")))
A16: مشتریان جدید | B16: =SUMPRODUCT((Customers!$A$4:$A$151<>"")*(LEFT(Customers!$G$4:$G$151,7)=TEXT(تنظیمات!$B$2,"0")&"/"&IF(تنظیمات!$D$2<10,"0","")&TEXT(تنظیمات!$D$2,"0"))) | C16: نفر | D16: =تنظیمات!C27 | E16: =IF(B16="","—",IF(B16>=D16,"مطلوب",IF(B16>=تنظیمات!D27,"نیاز به بررسی","بحرانی"))) | F16: =IF(E16="بحرانی",تنظیمات!G27,IF(E16="نیاز به بررسی","زیر نظر بگیرید — اگر تا پایان هفته سبز نشد اقدام کنید",IF(E16="مطلوب","","")))
A17: مبلغ وصول‌شده | B17: =SUMIFS(Sales!$M$4:$M$151,Sales!$P$4:$P$151,تنظیمات!$B$2,Sales!$Q$4:$Q$151,تنظیمات!$D$2) | C17: تومان | D17: =تنظیمات!C28 | E17: =IF(B17="","—",IF(B17>=D17,"مطلوب",IF(B17>=تنظیمات!D28,"نیاز به بررسی","بحرانی"))) | F17: =IF(E17="بحرانی",تنظیمات!G28,IF(E17="نیاز به بررسی","زیر نظر بگیرید — اگر تا پایان هفته سبز نشد اقدام کنید",IF(E17="مطلوب","","")))
A18: مطالبات (مانده باز) | B18: =SUMIF(Sales!$N$4:$N$151,">0") | C18: تومان | D18: =تنظیمات!C29 | E18: =IF(B18="","—",IF(B18<=D18,"مطلوب",IF(B18<=تنظیمات!D29,"نیاز به بررسی","بحرانی"))) | F18: =IF(E18="بحرانی",تنظیمات!G29,IF(E18="نیاز به بررسی","زیر نظر بگیرید — اگر تا پایان هفته سبز نشد اقدام کنید",IF(E18="مطلوب","","")))
A19: هزینه‌ها | B19: =SUMIFS(Expenses!$D$4:$D$151,Expenses!$H$4:$H$151,تنظیمات!$B$2,Expenses!$I$4:$I$151,تنظیمات!$D$2) | C19: تومان | D19: =تنظیمات!C30 | E19: =IF(B19="","—",IF(B19<=D19,"مطلوب",IF(B19<=تنظیمات!D30,"نیاز به بررسی","بحرانی"))) | F19: =IF(E19="بحرانی",تنظیمات!G30,IF(E19="نیاز به بررسی","زیر نظر بگیرید — اگر تا پایان هفته سبز نشد اقدام کنید",IF(E19="مطلوب","","")))
A20: درصد انجام ویزیت | B20: =IFERROR(SUMIFS(SalesRep!$E$4:$E$151,SalesRep!$O$4:$O$151,تنظیمات!$B$2,SalesRep!$P$4:$P$151,تنظیمات!$D$2)/SUMIFS(SalesRep!$D$4:$D$151,SalesRep!$O$4:$O$151,تنظیمات!$B$2,SalesRep!$P$4:$P$151,تنظیمات!$D$2),0) | C20: درصد | D20: =تنظیمات!C31 | E20: =IF(B20="","—",IF(B20>=D20,"مطلوب",IF(B20>=تنظیمات!D31,"نیاز به بررسی","بحرانی"))) | F20: =IF(E20="بحرانی",تنظیمات!G31,IF(E20="نیاز به بررسی","زیر نظر بگیرید — اگر تا پایان هفته سبز نشد اقدام کنید",IF(E20="مطلوب","","")))
A21: نرخ تبدیل ویزیت به سفارش | B21: =IFERROR(SUMIFS(SalesRep!$F$4:$F$151,SalesRep!$O$4:$O$151,تنظیمات!$B$2,SalesRep!$P$4:$P$151,تنظیمات!$D$2)/SUMIFS(SalesRep!$E$4:$E$151,SalesRep!$O$4:$O$151,تنظیمات!$B$2,SalesRep!$P$4:$P$151,تنظیمات!$D$2),0) | C21: درصد | D21: =تنظیمات!C32 | E21: =IF(B21="","—",IF(B21>=D21,"مطلوب",IF(B21>=تنظیمات!D32,"نیاز به بررسی","بحرانی"))) | F21: =IF(E21="بحرانی",تنظیمات!G32,IF(E21="نیاز به بررسی","زیر نظر بگیرید — اگر تا پایان هفته سبز نشد اقدام کنید",IF(E21="مطلوب","","")))
A22: درصد بارهای قبول‌شده | B22: =IFERROR(COUNTIFS(Purchases!$M$4:$M$151,تنظیمات!$B$2,Purchases!$N$4:$N$151,تنظیمات!$D$2,Purchases!$K$4:$K$151,"تأیید شده")/COUNTIFS(Purchases!$M$4:$M$151,تنظیمات!$B$2,Purchases!$N$4:$N$151,تنظیمات!$D$2,Purchases!$B$4:$B$151,"<>"),0) | C22: درصد | D22: =تنظیمات!C33 | E22: =IF(B22="","—",IF(B22>=D22,"مطلوب",IF(B22>=تنظیمات!D33,"نیاز به بررسی","بحرانی"))) | F22: =IF(E22="بحرانی",تنظیمات!G33,IF(E22="نیاز به بررسی","زیر نظر بگیرید — اگر تا پایان هفته سبز نشد اقدام کنید",IF(E22="مطلوب","","")))
A23: چرخه کار: ثبت در برگه‌ها → محاسبه خودکار KPI → نگاه ۱۰ دقیقه‌ای به این صفحه → فقط روی قرمز/زرد اقدام → اصلاح
A41: راهنمای سریع رنگ‌ها
A42: مطلوب — ادامه بده | C42: نیاز به بررسی — این هفته زیر نظر | F42: بحرانی — امروز اقدام

Sheet تنظیمات
A1: تنظیمات و اهداف قابل‌تغییر — این اعداد چراغ داشبورد را عوض می‌کنند
A2: سال | B2: 1405 | C2: ماه | D2: 6 | E2: تاریخ امروز | F2: 1405/06/18
B4: مقدار | C4: توضیح
A5: سال جاری | B5: =$B$2 | C5: سال شمسی گزارش داشبورد
A6: ماه جاری | B6: =$D$2 | C6: ۱ تا ۱۲ — الان شهریور
A7: تاریخ امروز | B7: =$F$2 | C7: هر روز این را عوض کنید (فروش روزانه از روی این تاریخ است)
A8: نام کارگاه | B8: کارگاه بسته‌بندی حبوبات پلدختر
A9: شهر | B9: پلدختر
A10: آستانه مشتری A (تومان) | B10: 20000000 | C10: مجموع خرید بالاتر از این = مشتری A
A11: آستانه مشتری B (تومان) | B11: 5000000 | C11: بین B و A = مشتری B، کمتر = C
A12: حداقل موجودی مواد (کیلو) | B12: 200 | C12: کمتر از این در انبار مواد = هشدار
A13: حداقل موجودی محصول (کیلو) | B13: 80 | C13: کمتر از این در محصول نهایی = هشدار
A16: ۲) اهداف KPI — مقدار مطلوب و آستانه بررسی را خودتان عوض کنید
A17: شناسه | B17: شاخص | C17: هدف مطلوب (سبز) | D17: آستانه بررسی (زرد) | E17: جهت | F17: واحد | G17: اقدام وقتی قرمز شد
A18: sales_day | B18: فروش روزانه | C18: 3000000 | D18: 1500000 | E18: higher | F18: تومان | G18: امروز فروش ضعیف است. با ویزیتور تماس بگیرید و مسیر را چک کنید.
A19: sales_month | B19: فروش ماهانه | C19: 80000000 | D19: 50000000 | E19: higher | F19: تومان | G19: فروش ماه از کف فاصله گرفته. برنامه ویزیت و تخفیف هدفمند بگذارید.
A20: gross_profit | B20: سود ناخالص | C20: 15000000 | D20: 3000000 | E20: higher | F20: تومان | G20: سود ناکافی است. قیمت خرید یا فروش یا هزینه‌ها را بازبینی کنید.
A21: purchases | B21: خرید مواد اولیه | C21: — | D21: — | E21: info | F21: تومان
A22: raw_stock | B22: موجودی مواد اولیه | C22: 200 | D22: 80 | E22: higher | F22: کیلوگرم | G22: مواد اولیه رو به اتمام است. امروز خرید هماهنگ کنید.
A23: fin_stock | B23: موجودی محصول نهایی | C23: 80 | D23: 30 | E23: higher | F23: کیلوگرم | G23: محصول آماده کم است. خط تولید را اولویت بدهید.
A24: production | B24: مقدار تولید | C24: 700 | D24: 350 | E24: higher | F24: کیلوگرم | G24: تولید این ماه کم است. برنامه پاک‌کنی و بسته‌بندی را ببینید.
A25: waste | B25: درصد ضایعات | C25: 0.03 | D25: 0.06 | E25: lower | F25: درصد | G25: ضایعات بحرانی است. کیفیت خرید و کار پاک‌کنی را همان امروز بررسی کنید.
A26: orders | B26: تعداد سفارش‌ها | C26: 15 | D26: 8 | E26: higher | F26: عدد | G26: سفارش کم است. ویزیتور باید مسیرهای خوابیده را بیدار کند.
A27: new_cust | B27: مشتریان جدید | C27: 3 | D27: 1 | E27: higher | F27: نفر | G27: مشتری جدید جذب نشده. یک نیم‌روز را به مشتری‌یابی اختصاص دهید.
A28: collected | B28: مبلغ وصول‌شده | C28: 50000000 | D28: 30000000 | E28: higher | F28: تومان | G28: وصول ضعیف است. مطالبات مشتری‌های A را امروز پیگیری کنید.
A29: receivables | B29: مطالبات | C29: 12000000 | D29: 25000000 | E29: lower | F29: تومان | G29: مطالبات بالاست. تا وصول نشود سفارش نسیه جدید ندهید.
A30: expenses | B30: هزینه‌ها | C30: 25000000 | D30: 45000000 | E30: lower | F30: تومان | G30: هزینه از سقف گذشته. خرید غیرضروری را متوقف کنید.
A31: visit_rate | B31: درصد انجام ویزیت | C31: 0.8 | D31: 0.6 | E31: higher | F31: درصد | G31: ویزیت‌ها طبق برنامه نیست. علت جا ماندن مسیر را بپرسید.
A32: conversion | B32: نرخ تبدیل ویزیت به سفارش | C32: 0.4 | D32: 0.25 | E32: higher | F32: درصد | G32: ویزیت به فروش تبدیل نمی‌شود. قیمت، موجودی یا کیفیت را بررسی کنید.
A33: accept_rate | B33: درصد بارهای قبول‌شده | C33: 0.9 | D33: 0.75 | E33: higher | F33: درصد | G33: بارهای زیادی رد می‌شود. تأمین‌کننده را عوض یا تذکر دهید.
A35: ۳) معنی چراغ‌ها
A36: مطلوب | B36: همه‌چیز در محدوده هدف است. دخالت لازم نیست.
A37: نیاز به بررسی | B37: در حال فاصله گرفتن از هدف. این هفته زیر نظر بگیرید.
A38: بحرانی | B38: همان روز اقدام کنید. متن اقدام در ستون آخر جدول بالاست.
A39: — | B39: شاخص اطلاعاتی است یا هنوز داده‌ای وارد نشده.
A41: نکته تاریخ شمسی: تاریخ‌ها را همیشه به صورت متن ۱۰ کاراکتری سال/ماه/روز وارد کنید؛ مثال ۱۴۰۵/۰۶/۱۸ را با اعداد انگلیسی بنویسید: 1405/06/18. سال و ماه داشبورد از ردیف ۲ همین برگه خوانده می‌شود. سلول‌های کرم‌رنگ را می‌توانید عوض کنید؛ سلول‌های خاکستری فرمول هستند.

Sheet Purchases
A1: خرید مواد اولیه
A2: سلول کرم = ورود اطلاعات | خاکستری = محاسبه خودکار | تاریخ: 1405/06/18 | فقط بار «تأیید شده» وارد موجودی و هزینه می‌شود
A3: ردیف | B3: تاریخ شمسی | C3: تأمین‌کننده | D3: نوع حبوبات | E3: مقدار (کیلو) | F3: قیمت هر کیلو | G3: مبلغ کل | H3: هزینه حمل | I3: قیمت تمام‌شده هر کیلو | J3: کیفیت | K3: وضعیت تأیید | L3: توضیحات | M3: سال | N3: ماه
A4: =IF(B4="","",ROW()-3) | B4: 1405/04/18 | C4: موجودی اول دوره | D4: لوبیا چیتی | E4: 180 | F4: 90000 | G4: =IF(OR(E4="",F4=""),"",E4*F4) | H4: 0 | I4: =IF(OR(E4="",E4=0),"",(G4+IF(H4="",0,H4))/E4) | J4: خوب | K4: تأیید شده | L4: موجودی ابتدای کار | M4: =IF(B4="","",VALUE(LEFT(B4,4))) | N4: =IF(B4="","",VALUE(MID(B4,6,2)))
A5: =IF(B5="","",ROW()-3) | B5: 1405/04/18 | C5: موجودی اول دوره | D5: عدس | E5: 80 | F5: 74000 | G5: =IF(OR(E5="",F5=""),"",E5*F5) | H5: 0 | I5: =IF(OR(E5="",E5=0),"",(G5+IF(H5="",0,H5))/E5) | J5: خوب | K5: تأیید شده | L5: موجودی ابتدای کار | M5: =IF(B5="","",VALUE(LEFT(B5,4))) | N5: =IF(B5="","",VALUE(MID(B5,6,2)))
A6: =IF(B6="","",ROW()-3) | B6: 1405/04/18 | C6: موجودی اول دوره | D6: نخود | E6: 90 | F6: 66000 | G6: =IF(OR(E6="",F6=""),"",E6*F6) | H6: 0 | I6: =IF(OR(E6="",E6=0),"",(G6+IF(H6="",0,H6))/E6) | J6: خوب | K6: تأیید شده | L6: موجودی ابتدای کار | M6: =IF(B6="","",VALUE(LEFT(B6,4))) | N6: =IF(B6="","",VALUE(MID(B6,6,2)))
A7: =IF(B7="","",ROW()-3) | B7: 1405/05/20 | C7: کشاورز بروجرد | D7: لوبیا قرمز | E7: 120 | F7: 84000 | G7: =IF(OR(E7="",F7=""),"",E7*F7) | H7: 1800000 | I7: =IF(OR(E7="",E7=0),"",(G7+IF(H7="",0,H7))/E7) | J7: خوب | K7: تأیید شده | M7: =IF(B7="","",VALUE(LEFT(B7,4))) | N7: =IF(B7="","",VALUE(MID(B7,6,2)))
A8: =IF(B8="","",ROW()-3) | B8: 1405/06/02 | C8: کشاورز بروجرد | D8: لوبیا چیتی | E8: 400 | F8: 92000 | G8: =IF(OR(E8="",F8=""),"",E8*F8) | H8: 2500000 | I8: =IF(OR(E8="",E8=0),"",(G8+IF(H8="",0,H8))/E8) | J8: عالی | K8: تأیید شده | L8: بار تازه | M8: =IF(B8="","",VALUE(LEFT(B8,4))) | N8: =IF(B8="","",VALUE(MID(B8,6,2)))
A9: =IF(B9="","",ROW()-3) | B9: 1405/06/04 | C9: اتحادیه نخود کوهدشت | D9: نخود | E9: 300 | F9: 68000 | G9: =IF(OR(E9="",F9=""),"",E9*F9) | H9: 1600000 | I9: =IF(OR(E9="",E9=0),"",(G9+IF(H9="",0,H9))/E9) | J9: خوب | K9: تأیید شده | M9: =IF(B9="","",VALUE(LEFT(B9,4))) | N9: =IF(B9="","",VALUE(MID(B9,6,2)))
A10: =IF(B10="","",ROW()-3) | B10: 1405/06/07 | C10: بازرگانی حبوبات خرم‌آباد | D10: عدس | E10: 250 | F10: 76000 | G10: =IF(OR(E10="",F10=""),"",E10*F10) | H10: 1400000 | I10: =IF(OR(E10="",E10=0),"",(G10+IF(H10="",0,H10))/E10) | J10: خوب | K10: تأیید شده | M10: =IF(B10="","",VALUE(LEFT(B10,4))) | N10: =IF(B10="","",VALUE(MID(B10,6,2)))
A11: =IF(B11="","",ROW()-3) | B11: 1405/06/08 | C11: تأمین عدس دزفول | D11: عدس | E11: 100 | F11: 79000 | G11: =IF(OR(E11="",F11=""),"",E11*F11) | H11: 900000 | I11: =IF(OR(E11="",E11=0),"",(G11+IF(H11="",0,H11))/E11) | J11: ضعیف | K11: رد شده | L11: ناخالصی زیاد — برگشت | M11: =IF(B11="","",VALUE(LEFT(B11,4))) | N11: =IF(B11="","",VALUE(MID(B11,6,2)))
A12: =IF(B12="","",ROW()-3) | B12: 1405/06/10 | C12: کشاورز بروجرد | D12: لوبیا قرمز | E12: 200 | F12: 85000 | G12: =IF(OR(E12="",F12=""),"",E12*F12) | H12: 1500000 | I12: =IF(OR(E12="",E12=0),"",(G12+IF(H12="",0,H12))/E12) | J12: خوب | K12: تأیید شده | M12: =IF(B12="","",VALUE(LEFT(B12,4))) | N12: =IF(B12="","",VALUE(MID(B12,6,2)))
A13: =IF(B13="","",ROW()-3) | B13: 1405/06/14 | C13: تأمین عدس دزفول | D13: لپه | E13: 150 | F13: 80000 | G13: =IF(OR(E13="",F13=""),"",E13*F13) | H13: 1100000 | I13: =IF(OR(E13="",E13=0),"",(G13+IF(H13="",0,H13))/E13) | J13: متوسط | K13: تأیید شده | L13: با کمی نخاله | M13: =IF(B13="","",VALUE(LEFT(B13,4))) | N13: =IF(B13="","",VALUE(MID(B13,6,2)))
A14: =IF(B14="","",ROW()-3) | B14: 1405/06/16 | C14: کشت و صنعت لرستان | D14: لوبیا سفید | E14: 180 | F14: 90000 | G14: =IF(OR(E14="",F14=""),"",E14*F14) | H14: 1300000 | I14: =IF(OR(E14="",E14=0),"",(G14+IF(H14="",0,H14))/E14) | J14: عالی | K14: تأیید شده | M14: =IF(B14="","",VALUE(LEFT(B14,4))) | N14: =IF(B14="","",VALUE(MID(B14,6,2)))
A15: =IF(B15="","",ROW()-3) | B15: 1405/06/17 | C15: اتحادیه نخود کوهدشت | D15: ماش | E15: 80 | F15: 72000 | G15: =IF(OR(E15="",F15=""),"",E15*F15) | H15: 700000 | I15: =IF(OR(E15="",E15=0),"",(G15+IF(H15="",0,H15))/E15) | J15: خوب | K15: در انتظار | L15: هنوز کنترل کیفیت نشده | M15: =IF(B15="","",VALUE(LEFT(B15,4))) | N15: =IF(B15="","",VALUE(MID(B15,6,2)))
A16: =IF(B16="","",ROW()-3) | G16: =IF(OR(E16="",F16=""),"",E16*F16) | I16: =IF(OR(E16="",E16=0),"",(G16+IF(H16="",0,H16))/E16) | M16: =IF(B16="","",VALUE(LEFT(B16,4))) | N16: =IF(B16="","",VALUE(MID(B16,6,2)))
A17: =IF(B17="","",ROW()-3) | G17: =IF(OR(E17="",F17=""),"",E17*F17) | I17: =IF(OR(E17="",E17=0),"",(G17+IF(H17="",0,H17))/E17) | M17: =IF(B17="","",VALUE(LEFT(B17,4))) | N17: =IF(B17="","",VALUE(MID(B17,6,2)))
A18: =IF(B18="","",ROW()-3) | G18: =IF(OR(E18="",F18=""),"",E18*F18) | I18: =IF(OR(E18="",E18=0),"",(G18+IF(H18="",0,H18))/E18) | M18: =IF(B18="","",VALUE(LEFT(B18,4))) | N18: =IF(B18="","",VALUE(MID(B18,6,2)))
A19: =IF(B19="","",ROW()-3) | G19: =IF(OR(E19="",F19=""),"",E19*F19) | I19: =IF(OR(E19="",E19=0),"",(G19+IF(H19="",0,H19))/E19) | M19: =IF(B19="","",VALUE(LEFT(B19,4))) | N19: =IF(B19="","",VALUE(MID(B19,6,2)))
A20: =IF(B20="","",ROW()-3) | G20: =IF(OR(E20="",F20=""),"",E20*F20) | I20: =IF(OR(E20="",E20=0),"",(G20+IF(H20="",0,H20))/E20) | M20: =IF(B20="","",VALUE(LEFT(B20,4))) | N20: =IF(B20="","",VALUE(MID(B20,6,2)))
A21: =IF(B21="","",ROW()-3) | G21: =IF(OR(E21="",F21=""),"",E21*F21) | I21: =IF(OR(E21="",E21=0),"",(G21+IF(H21="",0,H21))/E21) | M21: =IF(B21="","",VALUE(LEFT(B21,4))) | N21: =IF(B21="","",VALUE(MID(B21,6,2)))
A22: =IF(B22="","",ROW()-3) | G22: =IF(OR(E22="",F22=""),"",E22*F22) | I22: =IF(OR(E22="",E22=0),"",(G22+IF(H22="",0,H22))/E22) | M22: =IF(B22="","",VALUE(LEFT(B22,4))) | N22: =IF(B22="","",VALUE(MID(B22,6,2)))
A23: =IF(B23="","",ROW()-3) | G23: =IF(OR(E23="",F23=""),"",E23*F23) | I23: =IF(OR(E23="",E23=0),"",(G23+IF(H23="",0,H23))/E23) | M23: =IF(B23="","",VALUE(LEFT(B23,4))) | N23: =IF(B23="","",VALUE(MID(B23,6,2)))
A24: =IF(B24="","",ROW()-3) | G24: =IF(OR(E24="",F24=""),"",E24*F24) | I24: =IF(OR(E24="",E24=0),"",(G24+IF(H24="",0,H24))/E24) | M24: =IF(B24="","",VALUE(LEFT(B24,4))) | N24: =IF(B24="","",VALUE(MID(B24,6,2)))
A25: =IF(B25="","",ROW()-3) | G25: =IF(OR(E25="",F25=""),"",E25*F25) | I25: =IF(OR(E25="",E25=0),"",(G25+IF(H25="",0,H25))/E25) | M25: =IF(B25="","",VALUE(LEFT(B25,4))) | N25: =IF(B25="","",VALUE(MID(B25,6,2)))
A26: =IF(B26="","",ROW()-3) | G26: =IF(OR(E26="",F26=""),"",E26*F26) | I26: =IF(OR(E26="",E26=0),"",(G26+IF(H26="",0,H26))/E26) | M26: =IF(B26="","",VALUE(LEFT(B26,4))) | N26: =IF(B26="","",VALUE(MID(B26,6,2)))
A27: =IF(B27="","",ROW()-3) | G27: =IF(OR(E27="",F27=""),"",E27*F27) | I27: =IF(OR(E27="",E27=0),"",(G27+IF(H27="",0,H27))/E27) | M27: =IF(B27="","",VALUE(LEFT(B27,4))) | N27: =IF(B27="","",VALUE(MID(B27,6,2)))
... A151: =IF(B151="","",ROW()-3) | G151: =IF(OR(E151="",F151=""),"",E151*F151) | I151: =IF(OR(E151="",E151=0),"",(G151+IF(H151="",0,H151))/E151) | M151: =IF(B151="","",VALUE(LEFT(B151,4))) | N151: =IF(B151="","",VALUE(MID(B151,6,2)))

Sheet Inventory
A1: موجودی — خلاصه خودکار از خرید / تولید / فروش + دفتر تعدیل
A2: این برگه را پدر/مسئول انبار می‌بیند. خرید و فروش را دوباره وارد نکنید — خودکار حساب می‌شود. فقط شمارش و ضایعات انبار را پایین بزنید.
A3: الف) خلاصه موجودی لحظه‌ای
A4: نوع موجودی | B4: محصول | C4: موجودی محاسبه‌شده | D4: واحد | E4: حداقل | F4: وضعیت | G4: محل نگهداری | H4: نکته
A5: مواد اولیه | B5: لوبیا چیتی | C5: =SUMIFS(Purchases!$E$4:$E$151,Purchases!$D$4:$D$151,B5,Purchases!$K$4:$K$151,"تأیید شده")-SUMIFS(Production!$D$4:$D$151,Production!$C$4:$C$151,B5)+SUMIFS($D$50:$D$90,$C$50:$C$90,B5,$B$50:$B$90,A5)-SUMIFS($E$50:$E$90,$C$50:$C$90,B5,$B$50:$B$90,A5) | D5: کیلوگرم | E5: 25 | F5: =IF(C5="","—",IF(C5>=E5,"مطلوب",IF(C5>=E5*0.4,"نیاز به بررسی","بحرانی"))) | G5: انبار مواد اولیه | H5: =IF(C5<0,"خطا: خروجی بیشتر از ورودی","")
A6: مواد اولیه | B6: لوبیا قرمز | C6: =SUMIFS(Purchases!$E$4:$E$151,Purchases!$D$4:$D$151,B6,Purchases!$K$4:$K$151,"تأیید شده")-SUMIFS(Production!$D$4:$D$151,Production!$C$4:$C$151,B6)+SUMIFS($D$50:$D$90,$C$50:$C$90,B6,$B$50:$B$90,A6)-SUMIFS($E$50:$E$90,$C$50:$C$90,B6,$B$50:$B$90,A6) | D6: کیلوگرم | E6: 25 | F6: =IF(C6="","—",IF(C6>=E6,"مطلوب",IF(C6>=E6*0.4,"نیاز به بررسی","بحرانی"))) | G6: انبار مواد اولیه | H6: =IF(C6<0,"خطا: خروجی بیشتر از ورودی","")
A7: مواد اولیه | B7: لوبیا سفید | C7: =SUMIFS(Purchases!$E$4:$E$151,Purchases!$D$4:$D$151,B7,Purchases!$K$4:$K$151,"تأیید شده")-SUMIFS(Production!$D$4:$D$151,Production!$C$4:$C$151,B7)+SUMIFS($D$50:$D$90,$C$50:$C$90,B7,$B$50:$B$90,A7)-SUMIFS($E$50:$E$90,$C$50:$C$90,B7,$B$50:$B$90,A7) | D7: کیلوگرم | E7: 25 | F7: =IF(C7="","—",IF(C7>=E7,"مطلوب",IF(C7>=E7*0.4,"نیاز به بررسی","بحرانی"))) | G7: انبار مواد اولیه | H7: =IF(C7<0,"خطا: خروجی بیشتر از ورودی","")
A8: مواد اولیه | B8: عدس | C8: =SUMIFS(Purchases!$E$4:$E$151,Purchases!$D$4:$D$151,B8,Purchases!$K$4:$K$151,"تأیید شده")-SUMIFS(Production!$D$4:$D$151,Production!$C$4:$C$151,B8)+SUMIFS($D$50:$D$90,$C$50:$C$90,B8,$B$50:$B$90,A8)-SUMIFS($E$50:$E$90,$C$50:$C$90,B8,$B$50:$B$90,A8) | D8: کیلوگرم | E8: 25 | F8: =IF(C8="","—",IF(C8>=E8,"مطلوب",IF(C8>=E8*0.4,"نیاز به بررسی","بحرانی"))) | G8: انبار مواد اولیه | H8: =IF(C8<0,"خطا: خروجی بیشتر از ورودی","")
A9: مواد اولیه | B9: نخود | C9: =SUMIFS(Purchases!$E$4:$E$151,Purchases!$D$4:$D$151,B9,Purchases!$K$4:$K$151,"تأیید شده")-SUMIFS(Production!$D$4:$D$151,Production!$C$4:$C$151,B9)+SUMIFS($D$50:$D$90,$C$50:$C$90,B9,$B$50:$B$90,A9)-SUMIFS($E$50:$E$90,$C$50:$C$90,B9,$B$50:$B$90,A9) | D9: کیلوگرم | E9: 25 | F9: =IF(C9="","—",IF(C9>=E9,"مطلوب",IF(C9>=E9*0.4,"نیاز به بررسی","بحرانی"))) | G9: انبار مواد اولیه | H9: =IF(C9<0,"خطا: خروجی بیشتر از ورودی","")
A10: مواد اولیه | B10: لپه | C10: =SUMIFS(Purchases!$E$4:$E$151,Purchases!$D$4:$D$151,B10,Purchases!$K$4:$K$151,"تأیید شده")-SUMIFS(Production!$D$4:$D$151,Production!$C$4:$C$151,B10)+SUMIFS($D$50:$D$90,$C$50:$C$90,B10,$B$50:$B$90,A10)-SUMIFS($E$50:$E$90,$C$50:$C$90,B10,$B$50:$B$90,A10) | D10: کیلوگرم | E10: 25 | F10: =IF(C10="","—",IF(C10>=E10,"مطلوب",IF(C10>=E10*0.4,"نیاز به بررسی","بحرانی"))) | G10: انبار مواد اولیه | H10: =IF(C10<0,"خطا: خروجی بیشتر از ورودی","")
A11: مواد اولیه | B11: ماش | C11: =SUMIFS(Purchases!$E$4:$E$151,Purchases!$D$4:$D$151,B11,Purchases!$K$4:$K$151,"تأیید شده")-SUMIFS(Production!$D$4:$D$151,Production!$C$4:$C$151,B11)+SUMIFS($D$50:$D$90,$C$50:$C$90,B11,$B$50:$B$90,A11)-SUMIFS($E$50:$E$90,$C$50:$C$90,B11,$B$50:$B$90,A11) | D11: کیلوگرم | E11: 25 | F11: =IF(C11="","—",IF(C11>=E11,"مطلوب",IF(C11>=E11*0.4,"نیاز به بررسی","بحرانی"))) | G11: انبار مواد اولیه | H11: =IF(C11<0,"خطا: خروجی بیشتر از ورودی","")
A12: محصول نهایی (کیلو — از مقدار پاک‌شده منهای فروش)
A13: نوع موجودی | B13: محصول | C13: موجودی محاسبه‌شده | D13: واحد | E13: حداقل | F13: وضعیت | G13: محل نگهداری | H13: نکته
A14: محصول نهایی | B14: لوبیا چیتی | C14: =SUMIFS(Production!$E$4:$E$151,Production!$C$4:$C$151,B14)-SUMIFS(Sales!$H$4:$H$151,Sales!$E$4:$E$151,B14)+SUMIFS($D$50:$D$90,$C$50:$C$90,B14,$B$50:$B$90,A14)-SUMIFS($E$50:$E$90,$C$50:$C$90,B14,$B$50:$B$90,A14) | D14: کیلوگرم | E14: 15 | F14: =IF(C14="","—",IF(C14>=E14,"مطلوب",IF(C14>=E14*0.4,"نیاز به بررسی","بحرانی"))) | G14: انبار محصول نهایی | H14: =IF(C14<0,"خطا: فروش بیشتر از تولید","")
A15: محصول نهایی | B15: لوبیا قرمز | C15: =SUMIFS(Production!$E$4:$E$151,Production!$C$4:$C$151,B15)-SUMIFS(Sales!$H$4:$H$151,Sales!$E$4:$E$151,B15)+SUMIFS($D$50:$D$90,$C$50:$C$90,B15,$B$50:$B$90,A15)-SUMIFS($E$50:$E$90,$C$50:$C$90,B15,$B$50:$B$90,A15) | D15: کیلوگرم | E15: 15 | F15: =IF(C15="","—",IF(C15>=E15,"مطلوب",IF(C15>=E15*0.4,"نیاز به بررسی","بحرانی"))) | G15: انبار محصول نهایی | H15: =IF(C15<0,"خطا: فروش بیشتر از تولید","")
A16: محصول نهایی | B16: لوبیا سفید | C16: =SUMIFS(Production!$E$4:$E$151,Production!$C$4:$C$151,B16)-SUMIFS(Sales!$H$4:$H$151,Sales!$E$4:$E$151,B16)+SUMIFS($D$50:$D$90,$C$50:$C$90,B16,$B$50:$B$90,A16)-SUMIFS($E$50:$E$90,$C$50:$C$90,B16,$B$50:$B$90,A16) | D16: کیلوگرم | E16: 15 | F16: =IF(C16="","—",IF(C16>=E16,"مطلوب",IF(C16>=E16*0.4,"نیاز به بررسی","بحرانی"))) | G16: انبار محصول نهایی | H16: =IF(C16<0,"خطا: فروش بیشتر از تولید","")
A17: محصول نهایی | B17: عدس | C17: =SUMIFS(Production!$E$4:$E$151,Production!$C$4:$C$151,B17)-SUMIFS(Sales!$H$4:$H$151,Sales!$E$4:$E$151,B17)+SUMIFS($D$50:$D$90,$C$50:$C$90,B17,$B$50:$B$90,A17)-SUMIFS($E$50:$E$90,$C$50:$C$90,B17,$B$50:$B$90,A17) | D17: کیلوگرم | E17: 15 | F17: =IF(C17="","—",IF(C17>=E17,"مطلوب",IF(C17>=E17*0.4,"نیاز به بررسی","بحرانی"))) | G17: انبار محصول نهایی | H17: =IF(C17<0,"خطا: فروش بیشتر از تولید","")
A18: محصول نهایی | B18: نخود | C18: =SUMIFS(Production!$E$4:$E$151,Production!$C$4:$C$151,B18)-SUMIFS(Sales!$H$4:$H$151,Sales!$E$4:$E$151,B18)+SUMIFS($D$50:$D$90,$C$50:$C$90,B18,$B$50:$B$90,A18)-SUMIFS($E$50:$E$90,$C$50:$C$90,B18,$B$50:$B$90,A18) | D18: کیلوگرم | E18: 15 | F18: =IF(C18="","—",IF(C18>=E18,"مطلوب",IF(C18>=E18*0.4,"نیاز به بررسی","بحرانی"))) | G18: انبار محصول نهایی | H18: =IF(C18<0,"خطا: فروش بیشتر از تولید","")
A19: محصول نهایی | B19: لپه | C19: =SUMIFS(Production!$E$4:$E$151,Production!$C$4:$C$151,B19)-SUMIFS(Sales!$H$4:$H$151,Sales!$E$4:$E$151,B19)+SUMIFS($D$50:$D$90,$C$50:$C$90,B19,$B$50:$B$90,A19)-SUMIFS($E$50:$E$90,$C$50:$C$90,B19,$B$50:$B$90,A19) | D19: کیلوگرم | E19: 15 | F19: =IF(C19="","—",IF(C19>=E19,"مطلوب",IF(C19>=E19*0.4,"نیاز به بررسی","بحرانی"))) | G19: انبار محصول نهایی | H19: =IF(C19<0,"خطا: فروش بیشتر از تولید","")
A20: محصول نهایی | B20: ماش | C20: =SUMIFS(Production!$E$4:$E$151,Production!$C$4:$C$151,B20)-SUMIFS(Sales!$H$4:$H$151,Sales!$E$4:$E$151,B20)+SUMIFS($D$50:$D$90,$C$50:$C$90,B20,$B$50:$B$90,A20)-SUMIFS($E$50:$E$90,$C$50:$C$90,B20,$B$50:$B$90,A20) | D20: کیلوگرم | E20: 15 | F20: =IF(C20="","—",IF(C20>=E20,"مطلوب",IF(C20>=E20*0.4,"نیاز به بررسی","بحرانی"))) | G20: انبار محصول نهایی | H20: =IF(C20<0,"خطا: فروش بیشتر از تولید","")
A21: جمع مواد اولیه | C21: =SUM(C5:C11)
A22: جمع محصول نهایی | C22: =SUM(C14:C20)
A24: ب) موجودی بسته (تعداد بسته تولیدشده − تعداد فروش)
A25: محصول | B25: وزن بسته | C25: تولید بسته | D25: فروش بسته | E25: مانده بسته | F25: واحد
A26: لوبیا چیتی | B26: 0.4 | C26: =SUMIFS(Production!$I$4:$I$151,Production!$C$4:$C$151,A26,Production!$H$4:$H$151,B26) | D26: =SUMIFS(Sales!$G$4:$G$151,Sales!$E$4:$E$151,A26,Sales!$F$4:$F$151,B26) | E26: =C26-D26 | F26: بسته
A27: لوبیا چیتی | B27: 0.9 | C27: =SUMIFS(Production!$I$4:$I$151,Production!$C$4:$C$151,A27,Production!$H$4:$H$151,B27) | D27: =SUMIFS(Sales!$G$4:$G$151,Sales!$E$4:$E$151,A27,Sales!$F$4:$F$151,B27) | E27: =C27-D27 | F27: بسته
A28: لوبیا چیتی | B28: 10 | C28: =SUMIFS(Production!$I$4:$I$151,Production!$C$4:$C$151,A28,Production!$H$4:$H$151,B28) | D28: =SUMIFS(Sales!$G$4:$G$151,Sales!$E$4:$E$151,A28,Sales!$F$4:$F$151,B28) | E28: =C28-D28 | F28: بسته
A29: لوبیا قرمز | B29: 0.4 | C29: =SUMIFS(Production!$I$4:$I$151,Production!$C$4:$C$151,A29,Production!$H$4:$H$151,B29) | D29: =SUMIFS(Sales!$G$4:$G$151,Sales!$E$4:$E$151,A29,Sales!$F$4:$F$151,B29) | E29: =C29-D29 | F29: بسته
A30: لوبیا قرمز | B30: 0.9 | C30: =SUMIFS(Production!$I$4:$I$151,Production!$C$4:$C$151,A30,Production!$H$4:$H$151,B30) | D30: =SUMIFS(Sales!$G$4:$G$151,Sales!$E$4:$E$151,A30,Sales!$F$4:$F$151,B30) | E30: =C30-D30 | F30: بسته
A31: لوبیا قرمز | B31: 10 | C31: =SUMIFS(Production!$I$4:$I$151,Production!$C$4:$C$151,A31,Production!$H$4:$H$151,B31) | D31: =SUMIFS(Sales!$G$4:$G$151,Sales!$E$4:$E$151,A31,Sales!$F$4:$F$151,B31) | E31: =C31-D31 | F31: بسته
A32: لوبیا سفید | B32: 0.4 | C32: =SUMIFS(Production!$I$4:$I$151,Production!$C$4:$C$151,A32,Production!$H$4:$H$151,B32) | D32: =SUMIFS(Sales!$G$4:$G$151,Sales!$E$4:$E$151,A32,Sales!$F$4:$F$151,B32) | E32: =C32-D32 | F32: بسته
A33: لوبیا سفید | B33: 0.9 | C33: =SUMIFS(Production!$I$4:$I$151,Production!$C$4:$C$151,A33,Production!$H$4:$H$151,B33) | D33: =SUMIFS(Sales!$G$4:$G$151,Sales!$E$4:$E$151,A33,Sales!$F$4:$F$151,B33) | E33: =C33-D33 | F33: بسته
A34: لوبیا سفید | B34: 10 | C34: =SUMIFS(Production!$I$4:$I$151,Production!$C$4:$C$151,A34,Production!$H$4:$H$151,B34) | D34: =SUMIFS(Sales!$G$4:$G$151,Sales!$E$4:$E$151,A34,Sales!$F$4:$F$151,B34) | E34: =C34-D34 | F34: بسته
A35: عدس | B35: 0.4 | C35: =SUMIFS(Production!$I$4:$I$151,Production!$C$4:$C$151,A35,Production!$H$4:$H$151,B35) | D35: =SUMIFS(Sales!$G$4:$G$151,Sales!$E$4:$E$151,A35,Sales!$F$4:$F$151,B35) | E35: =C35-D35 | F35: بسته
A36: عدس | B36: 0.9 | C36: =SUMIFS(Production!$I$4:$I$151,Production!$C$4:$C$151,A36,Production!$H$4:$H$151,B36) | D36: =SUMIFS(Sales!$G$4:$G$151,Sales!$E$4:$E$151,A36,Sales!$F$4:$F$151,B36) | E36: =C36-D36 | F36: بسته
A37: عدس | B37: 10 | C37: =SUMIFS(Production!$I$4:$I$151,Production!$C$4:$C$151,A37,Production!$H$4:$H$151,B37) | D37: =SUMIFS(Sales!$G$4:$G$151,Sales!$E$4:$E$151,A37,Sales!$F$4:$F$151,B37) | E37: =C37-D37 | F37: بسته
... A46: ماش | B46: 10 | C46: =SUMIFS(Production!$I$4:$I$151,Production!$C$4:$C$151,A46,Production!$H$4:$H$151,B46) | D46: =SUMIFS(Sales!$G$4:$G$151,Sales!$E$4:$E$151,A46,Sales!$F$4:$F$151,B46) | E46: =C46-D46 | F46: بسته
A47: ج) دفتر حرکات دستی انبار (شمارش، ضایعات انبار، اصلاح)
A48: خرید و فروش را اینجا ننویسید. فقط وقتی شمارش با سیستم فرق دارد یا ضایعات انبار رخ داده.
A49: تاریخ شمسی | B49: نوع موجودی | C49: محصول | D49: ورود | E49: خروج | F49: موجودی این کالا (دفتر) | G49: واحد | H49: محل / علت
A50: 1405/06/09 | B50: مواد اولیه | C50: عدس | D50: 0 | E50: 2.5 | F50: =IF(C50="","",SUMIFS($D$50:D50,$C$50:C50,C50,$B$50:B50,B50)-SUMIFS($E$50:E50,$C$50:C50,C50,$B$50:B50,B50)) | G50: کیلوگرم | H50: سالن تولید — نمونه کنترل کیفیت
A51: 1405/06/13 | B51: محصول نهایی | C51: لوبیا چیتی | D51: 0 | E51: 1 | F51: =IF(C51="","",SUMIFS($D$50:D51,$C$50:C51,C51,$B$50:B51,B51)-SUMIFS($E$50:E51,$C$50:C51,C51,$B$50:B51,B51)) | G51: کیلوگرم | H51: انبار محصول نهایی — پارگی بسته — ضایعات
F52: =IF(C52="","",SUMIFS($D$50:D52,$C$50:C52,C52,$B$50:B52,B52)-SUMIFS($E$50:E52,$C$50:C52,C52,$B$50:B52,B52))
F53: =IF(C53="","",SUMIFS($D$50:D53,$C$50:C53,C53,$B$50:B53,B53)-SUMIFS($E$50:E53,$C$50:C53,C53,$B$50:B53,B53))
F54: =IF(C54="","",SUMIFS($D$50:D54,$C$50:C54,C54,$B$50:B54,B54)-SUMIFS($E$50:E54,$C$50:C54,C54,$B$50:B54,B54))
F55: =IF(C55="","",SUMIFS($D$50:D55,$C$50:C55,C55,$B$50:B55,B55)-SUMIFS($E$50:E55,$C$50:C55,C55,$B$50:B55,B55))
F56: =IF(C56="","",SUMIFS($D$50:D56,$C$50:C56,C56,$B$50:B56,B56)-SUMIFS($E$50:E56,$C$50:C56,C56,$B$50:B56,B56))
F57: =IF(C57="","",SUMIFS($D$50:D57,$C$50:C57,C57,$B$50:B57,B57)-SUMIFS($E$50:E57,$C$50:C57,C57,$B$50:B57,B57))
F58: =IF(C58="","",SUMIFS($D$50:D58,$C$50:C58,C58,$B$50:B58,B58)-SUMIFS($E$50:E58,$C$50:C58,C58,$B$50:B58,B58))
F59: =IF(C59="","",SUMIFS($D$50:D59,$C$50:C59,C59,$B$50:B59,B59)-SUMIFS($E$50:E59,$C$50:C59,C59,$B$50:B59,B59))
F60: =IF(C60="","",SUMIFS($D$50:D60,$C$50:C60,C60,$B$50:B60,B60)-SUMIFS($E$50:E60,$C$50:C60,C60,$B$50:B60,B60))
F61: =IF(C61="","",SUMIFS($D$50:D61,$C$50:C61,C61,$B$50:B61,B61)-SUMIFS($E$50:E61,$C$50:C61,C61,$B$50:B61,B61))
F62: =IF(C62="","",SUMIFS($D$50:D62,$C$50:C62,C62,$B$50:B62,B62)-SUMIFS($E$50:E62,$C$50:C62,C62,$B$50:B62,B62))
F63: =IF(C63="","",SUMIFS($D$50:D63,$C$50:C63,C63,$B$50:B63,B63)-SUMIFS($E$50:E63,$C$50:C63,C63,$B$50:B63,B63))
... F89: =IF(C89="","",SUMIFS($D$50:D89,$C$50:C89,C89,$B$50:B89,B89)-SUMIFS($E$50:E89,$C$50:C89,C89,$B$50:B89,B89))

Sheet Production
A1: تولید و بسته‌بندی
A2: ورود: تاریخ، نوع، مقدار ورودی، مقدار پاک‌شده، وزن بسته، اپراتور | ضایعات، درصد، تعداد بسته و خطای وزن خودکار است
A3: ردیف | B3: تاریخ شمسی | C3: نوع حبوبات | D3: مقدار ورودی (کیلو) | E3: مقدار پاک‌شده (کیلو) | F3: مقدار ضایعات | G3: درصد ضایعات | H3: وزن بسته (کیلو) | I3: تعداد بسته | J3: خطای وزن (کیلو) | K3: اپراتور | L3: توضیحات | M3: سال | N3: ماه
A4: =IF(B4="","",ROW()-3) | B4: 1405/05/22 | C4: لوبیا چیتی | D4: 80 | E4: 77.2 | F4: =IF(OR(D4="",E4=""),"",D4-E4) | G4: =IF(OR(D4="",D4=0),"",F4/D4) | H4: 0.9 | I4: =IF(OR(E4="",H4="",H4=0),"",INT(E4/H4)) | J4: =IF(OR(E4="",H4="",I4=""),"",E4-I4*H4) | K4: مسئول بسته‌بندی | M4: =IF(B4="","",VALUE(LEFT(B4,4))) | N4: =IF(B4="","",VALUE(MID(B4,6,2)))
A5: =IF(B5="","",ROW()-3) | B5: 1405/05/25 | C5: عدس | D5: 40 | E5: 38.4 | F5: =IF(OR(D5="",E5=""),"",D5-E5) | G5: =IF(OR(D5="",D5=0),"",F5/D5) | H5: 0.4 | I5: =IF(OR(E5="",H5="",H5=0),"",INT(E5/H5)) | J5: =IF(OR(E5="",H5="",I5=""),"",E5-I5*H5) | K5: مسئول بسته‌بندی | M5: =IF(B5="","",VALUE(LEFT(B5,4))) | N5: =IF(B5="","",VALUE(MID(B5,6,2)))
A6: =IF(B6="","",ROW()-3) | B6: 1405/06/03 | C6: لوبیا چیتی | D6: 120 | E6: 116.4 | F6: =IF(OR(D6="",E6=""),"",D6-E6) | G6: =IF(OR(D6="",D6=0),"",F6/D6) | H6: 0.4 | I6: =IF(OR(E6="",H6="",H6=0),"",INT(E6/H6)) | J6: =IF(OR(E6="",H6="",I6=""),"",E6-I6*H6) | K6: مسئول بسته‌بندی | M6: =IF(B6="","",VALUE(LEFT(B6,4))) | N6: =IF(B6="","",VALUE(MID(B6,6,2)))
A7: =IF(B7="","",ROW()-3) | B7: 1405/06/03 | C7: لوبیا چیتی | D7: 80 | E7: 77.6 | F7: =IF(OR(D7="",E7=""),"",D7-E7) | G7: =IF(OR(D7="",D7=0),"",F7/D7) | H7: 0.9 | I7: =IF(OR(E7="",H7="",H7=0),"",INT(E7/H7)) | J7: =IF(OR(E7="",H7="",I7=""),"",E7-I7*H7) | K7: مسئول بسته‌بندی | M7: =IF(B7="","",VALUE(LEFT(B7,4))) | N7: =IF(B7="","",VALUE(MID(B7,6,2)))
A8: =IF(B8="","",ROW()-3) | B8: 1405/06/05 | C8: نخود | D8: 100 | E8: 96.5 | F8: =IF(OR(D8="",E8=""),"",D8-E8) | G8: =IF(OR(D8="",D8=0),"",F8/D8) | H8: 0.9 | I8: =IF(OR(E8="",H8="",H8=0),"",INT(E8/H8)) | J8: =IF(OR(E8="",H8="",I8=""),"",E8-I8*H8) | K8: مسئول بسته‌بندی | M8: =IF(B8="","",VALUE(LEFT(B8,4))) | N8: =IF(B8="","",VALUE(MID(B8,6,2)))
A9: =IF(B9="","",ROW()-3) | B9: 1405/06/05 | C9: نخود | D9: 60 | E9: 58.2 | F9: =IF(OR(D9="",E9=""),"",D9-E9) | G9: =IF(OR(D9="",D9=0),"",F9/D9) | H9: 0.4 | I9: =IF(OR(E9="",H9="",H9=0),"",INT(E9/H9)) | J9: =IF(OR(E9="",H9="",I9=""),"",E9-I9*H9) | K9: پدر مدیر | L9: کمک تولید | M9: =IF(B9="","",VALUE(LEFT(B9,4))) | N9: =IF(B9="","",VALUE(MID(B9,6,2)))
A10: =IF(B10="","",ROW()-3) | B10: 1405/06/08 | C10: عدس | D10: 90 | E10: 86.4 | F10: =IF(OR(D10="",E10=""),"",D10-E10) | G10: =IF(OR(D10="",D10=0),"",F10/D10) | H10: 0.4 | I10: =IF(OR(E10="",H10="",H10=0),"",INT(E10/H10)) | J10: =IF(OR(E10="",H10="",I10=""),"",E10-I10*H10) | K10: مسئول بسته‌بندی | M10: =IF(B10="","",VALUE(LEFT(B10,4))) | N10: =IF(B10="","",VALUE(MID(B10,6,2)))
A11: =IF(B11="","",ROW()-3) | B11: 1405/06/09 | C11: عدس | D11: 70 | E11: 64 | F11: =IF(OR(D11="",E11=""),"",D11-E11) | G11: =IF(OR(D11="",D11=0),"",F11/D11) | H11: 0.9 | I11: =IF(OR(E11="",H11="",H11=0),"",INT(E11/H11)) | J11: =IF(OR(E11="",H11="",I11=""),"",E11-I11*H11) | K11: مسئول بسته‌بندی | L11: ضایعات بالاتر از معمول | M11: =IF(B11="","",VALUE(LEFT(B11,4))) | N11: =IF(B11="","",VALUE(MID(B11,6,2)))
A12: =IF(B12="","",ROW()-3) | B12: 1405/06/11 | C12: لوبیا قرمز | D12: 80 | E12: 77.2 | F12: =IF(OR(D12="",E12=""),"",D12-E12) | G12: =IF(OR(D12="",D12=0),"",F12/D12) | H12: 0.4 | I12: =IF(OR(E12="",H12="",H12=0),"",INT(E12/H12)) | J12: =IF(OR(E12="",H12="",I12=""),"",E12-I12*H12) | K12: مسئول بسته‌بندی | M12: =IF(B12="","",VALUE(LEFT(B12,4))) | N12: =IF(B12="","",VALUE(MID(B12,6,2)))
A13: =IF(B13="","",ROW()-3) | B13: 1405/06/12 | C13: لوبیا قرمز | D13: 70 | E13: 67.5 | F13: =IF(OR(D13="",E13=""),"",D13-E13) | G13: =IF(OR(D13="",D13=0),"",F13/D13) | H13: 0.9 | I13: =IF(OR(E13="",H13="",H13=0),"",INT(E13/H13)) | J13: =IF(OR(E13="",H13="",I13=""),"",E13-I13*H13) | K13: مسئول بسته‌بندی | M13: =IF(B13="","",VALUE(LEFT(B13,4))) | N13: =IF(B13="","",VALUE(MID(B13,6,2)))
A14: =IF(B14="","",ROW()-3) | B14: 1405/06/13 | C14: لوبیا چیتی | D14: 100 | E14: 97 | F14: =IF(OR(D14="",E14=""),"",D14-E14) | G14: =IF(OR(D14="",D14=0),"",F14/D14) | H14: 10 | I14: =IF(OR(E14="",H14="",H14=0),"",INT(E14/H14)) | J14: =IF(OR(E14="",H14="",I14=""),"",E14-I14*H14) | K14: پدر مدیر | L14: بسته ۱۰ کیلویی عمده | M14: =IF(B14="","",VALUE(LEFT(B14,4))) | N14: =IF(B14="","",VALUE(MID(B14,6,2)))
A15: =IF(B15="","",ROW()-3) | B15: 1405/06/15 | C15: لپه | D15: 80 | E15: 76.8 | F15: =IF(OR(D15="",E15=""),"",D15-E15) | G15: =IF(OR(D15="",D15=0),"",F15/D15) | H15: 0.9 | I15: =IF(OR(E15="",H15="",H15=0),"",INT(E15/H15)) | J15: =IF(OR(E15="",H15="",I15=""),"",E15-I15*H15) | K15: مسئول بسته‌بندی | M15: =IF(B15="","",VALUE(LEFT(B15,4))) | N15: =IF(B15="","",VALUE(MID(B15,6,2)))
A16: =IF(B16="","",ROW()-3) | B16: 1405/06/16 | C16: لوبیا سفید | D16: 90 | E16: 87.3 | F16: =IF(OR(D16="",E16=""),"",D16-E16) | G16: =IF(OR(D16="",D16=0),"",F16/D16) | H16: 0.4 | I16: =IF(OR(E16="",H16="",H16=0),"",INT(E16/H16)) | J16: =IF(OR(E16="",H16="",I16=""),"",E16-I16*H16) | K16: مسئول بسته‌بندی | M16: =IF(B16="","",VALUE(LEFT(B16,4))) | N16: =IF(B16="","",VALUE(MID(B16,6,2)))
A17: =IF(B17="","",ROW()-3) | B17: 1405/06/17 | C17: نخود | D17: 50 | E17: 48.5 | F17: =IF(OR(D17="",E17=""),"",D17-E17) | G17: =IF(OR(D17="",D17=0),"",F17/D17) | H17: 10 | I17: =IF(OR(E17="",H17="",H17=0),"",INT(E17/H17)) | J17: =IF(OR(E17="",H17="",I17=""),"",E17-I17*H17) | K17: پدر مدیر | M17: =IF(B17="","",VALUE(LEFT(B17,4))) | N17: =IF(B17="","",VALUE(MID(B17,6,2)))
A18: =IF(B18="","",ROW()-3) | B18: 1405/06/18 | C18: لوبیا چیتی | D18: 60 | E18: 57.6 | F18: =IF(OR(D18="",E18=""),"",D18-E18) | G18: =IF(OR(D18="",D18=0),"",F18/D18) | H18: 0.9 | I18: =IF(OR(E18="",H18="",H18=0),"",INT(E18/H18)) | J18: =IF(OR(E18="",H18="",I18=""),"",E18-I18*H18) | K18: مسئول بسته‌بندی | M18: =IF(B18="","",VALUE(LEFT(B18,4))) | N18: =IF(B18="","",VALUE(MID(B18,6,2)))
A19: =IF(B19="","",ROW()-3) | F19: =IF(OR(D19="",E19=""),"",D19-E19) | G19: =IF(OR(D19="",D19=0),"",F19/D19) | I19: =IF(OR(E19="",H19="",H19=0),"",INT(E19/H19)) | J19: =IF(OR(E19="",H19="",I19=""),"",E19-I19*H19) | M19: =IF(B19="","",VALUE(LEFT(B19,4))) | N19: =IF(B19="","",VALUE(MID(B19,6,2)))
A20: =IF(B20="","",ROW()-3) | F20: =IF(OR(D20="",E20=""),"",D20-E20) | G20: =IF(OR(D20="",D20=0),"",F20/D20) | I20: =IF(OR(E20="",H20="",H20=0),"",INT(E20/H20)) | J20: =IF(OR(E20="",H20="",I20=""),"",E20-I20*H20) | M20: =IF(B20="","",VALUE(LEFT(B20,4))) | N20: =IF(B20="","",VALUE(MID(B20,6,2)))
A21: =IF(B21="","",ROW()-3) | F21: =IF(OR(D21="",E21=""),"",D21-E21) | G21: =IF(OR(D21="",D21=0),"",F21/D21) | I21: =IF(OR(E21="",H21="",H21=0),"",INT(E21/H21)) | J21: =IF(OR(E21="",H21="",I21=""),"",E21-I21*H21) | M21: =IF(B21="","",VALUE(LEFT(B21,4))) | N21: =IF(B21="","",VALUE(MID(B21,6,2)))
A22: =IF(B22="","",ROW()-3) | F22: =IF(OR(D22="",E22=""),"",D22-E22) | G22: =IF(OR(D22="",D22=0),"",F22/D22) | I22: =IF(OR(E22="",H22="",H22=0),"",INT(E22/H22)) | J22: =IF(OR(E22="",H22="",I22=""),"",E22-I22*H22) | M22: =IF(B22="","",VALUE(LEFT(B22,4))) | N22: =IF(B22="","",VALUE(MID(B22,6,2)))
A23: =IF(B23="","",ROW()-3) | F23: =IF(OR(D23="",E23=""),"",D23-E23) | G23: =IF(OR(D23="",D23=0),"",F23/D23) | I23: =IF(OR(E23="",H23="",H23=0),"",INT(E23/H23)) | J23: =IF(OR(E23="",H23="",I23=""),"",E23-I23*H23) | M23: =IF(B23="","",VALUE(LEFT(B23,4))) | N23: =IF(B23="","",VALUE(MID(B23,6,2)))
A24: =IF(B24="","",ROW()-3) | F24: =IF(OR(D24="",E24=""),"",D24-E24) | G24: =IF(OR(D24="",D24=0),"",F24/D24) | I24: =IF(OR(E24="",H24="",H24=0),"",INT(E24/H24)) | J24: =IF(OR(E24="",H24="",I24=""),"",E24-I24*H24) | M24: =IF(B24="","",VALUE(LEFT(B24,4))) | N24: =IF(B24="","",VALUE(MID(B24,6,2)))
A25: =IF(B25="","",ROW()-3) | F25: =IF(OR(D25="",E25=""),"",D25-E25) | G25: =IF(OR(D25="",D25=0),"",F25/D25) | I25: =IF(OR(E25="",H25="",H25=0),"",INT(E25/H25)) | J25: =IF(OR(E25="",H25="",I25=""),"",E25-I25*H25) | M25: =IF(B25="","",VALUE(LEFT(B25,4))) | N25: =IF(B25="","",VALUE(MID(B25,6,2)))
A26: =IF(B26="","",ROW()-3) | F26: =IF(OR(D26="",E26=""),"",D26-E26) | G26: =IF(OR(D26="",D26=0),"",F26/D26) | I26: =IF(OR(E26="",H26="",H26=0),"",INT(E26/H26)) | J26: =IF(OR(E26="",H26="",I26=""),"",E26-I26*H26) | M26: =IF(B26="","",VALUE(LEFT(B26,4))) | N26: =IF(B26="","",VALUE(MID(B26,6,2)))
A27: =IF(B27="","",ROW()-3) | F27: =IF(OR(D27="",E27=""),"",D27-E27) | G27: =IF(OR(D27="",D27=0),"",F27/D27) | I27: =IF(OR(E27="",H27="",H27=0),"",INT(E27/H27)) | J27: =IF(OR(E27="",H27="",I27=""),"",E27-I27*H27) | M27: =IF(B27="","",VALUE(LEFT(B27,4))) | N27: =IF(B27="","",VALUE(MID(B27,6,2)))
A28: =IF(B28="","",ROW()-3) | F28: =IF(OR(D28="",E28=""),"",D28-E28) | G28: =IF(OR(D28="",D28=0),"",F28/D28) | I28: =IF(OR(E28="",H28="",H28=0),"",INT(E28/H28)) | J28: =IF(OR(E28="",H28="",I28=""),"",E28-I28*H28) | M28: =IF(B28="","",VALUE(LEFT(B28,4))) | N28: =IF(B28="","",VALUE(MID(B28,6,2)))
A29: =IF(B29="","",ROW()-3) | F29: =IF(OR(D29="",E29=""),"",D29-E29) | G29: =IF(OR(D29="",D29=0),"",F29/D29) | I29: =IF(OR(E29="",H29="",H29=0),"",INT(E29/H29)) | J29: =IF(OR(E29="",H29="",I29=""),"",E29-I29*H29) | M29: =IF(B29="","",VALUE(LEFT(B29,4))) | N29: =IF(B29="","",VALUE(MID(B29,6,2)))
A30: =IF(B30="","",ROW()-3) | F30: =IF(OR(D30="",E30=""),"",D30-E30) | G30: =IF(OR(D30="",D30=0),"",F30/D30) | I30: =IF(OR(E30="",H30="",H30=0),"",INT(E30/H30)) | J30: =IF(OR(E30="",H30="",I30=""),"",E30-I30*H30) | M30: =IF(B30="","",VALUE(LEFT(B30,4))) | N30: =IF(B30="","",VALUE(MID(B30,6,2)))
... A151: =IF(B151="","",ROW()-3) | F151: =IF(OR(D151="",E151=""),"",D151-E151) | G151: =IF(OR(D151="",D151=0),"",F151/D151) | I151: =IF(OR(E151="",H151="",H151=0),"",INT(E151/H151)) | J151: =IF(OR(E151="",H151="",I151=""),"",E151-I151*H151) | M151: =IF(B151="","",VALUE(LEFT(B151,4))) | N151: =IF(B151="","",VALUE(MID(B151,6,2)))

Sheet Sales
A1: فروش
A2: مبلغ فروش، مبلغ نهایی و مانده حساب خودکار است. وصول را همین‌جا بزنید تا مطالبات داشبورد درست بماند.
A3: ردیف | B3: تاریخ شمسی | C3: نام مشتری | D3: شهر/منطقه | E3: محصول | F3: وزن بسته (کیلو) | G3: تعداد | H3: وزن کل (کیلو) | I3: قیمت واحد | J3: مبلغ فروش | K3: تخفیف | L3: مبلغ نهایی | M3: مبلغ وصول‌شده | N3: مانده حساب | O3: فروشنده | P3: سال | Q3: ماه
A4: =IF(B4="","",ROW()-3) | B4: 1405/05/26 | C4: سوپرمارکت رضایی | D4: پلدختر | E4: لوبیا چیتی | F4: 0.9 | G4: 40 | H4: =IF(OR(F4="",G4=""),"",F4*G4) | I4: 98000 | J4: =IF(OR(G4="",I4=""),"",G4*I4) | K4: 0 | L4: =IF(J4="","",J4-IF(K4="",0,K4)) | M4: 3920000 | N4: =IF(L4="","",L4-IF(M4="",0,M4)) | O4: ویزیتور پخش | P4: =IF(B4="","",VALUE(LEFT(B4,4))) | Q4: =IF(B4="","",VALUE(MID(B4,6,2)))
A5: =IF(B5="","",ROW()-3) | B5: 1405/05/28 | C5: خواربار محمدی | D5: پلدختر | E5: عدس | F5: 0.4 | G5: 50 | H5: =IF(OR(F5="",G5=""),"",F5*G5) | I5: 42000 | J5: =IF(OR(G5="",I5=""),"",G5*I5) | K5: 0 | L5: =IF(J5="","",J5-IF(K5="",0,K5)) | M5: 2100000 | N5: =IF(L5="","",L5-IF(M5="",0,M5)) | O5: ویزیتور پخش | P5: =IF(B5="","",VALUE(LEFT(B5,4))) | Q5: =IF(B5="","",VALUE(MID(B5,6,2)))
A6: =IF(B6="","",ROW()-3) | B6: 1405/06/04 | C6: سوپرمارکت رضایی | D6: پلدختر | E6: لوبیا چیتی | F6: 0.4 | G6: 80 | H6: =IF(OR(F6="",G6=""),"",F6*G6) | I6: 46000 | J6: =IF(OR(G6="",I6=""),"",G6*I6) | K6: 80000 | L6: =IF(J6="","",J6-IF(K6="",0,K6)) | M6: 3600000 | N6: =IF(L6="","",L6-IF(M6="",0,M6)) | O6: ویزیتور پخش | P6: =IF(B6="","",VALUE(LEFT(B6,4))) | Q6: =IF(B6="","",VALUE(MID(B6,6,2)))
A7: =IF(B7="","",ROW()-3) | B7: 1405/06/04 | C7: سوپرمارکت رضایی | D7: پلدختر | E7: نخود | F7: 0.9 | G7: 30 | H7: =IF(OR(F7="",G7=""),"",F7*G7) | I7: 82000 | J7: =IF(OR(G7="",I7=""),"",G7*I7) | K7: 0 | L7: =IF(J7="","",J7-IF(K7="",0,K7)) | M7: 2460000 | N7: =IF(L7="","",L7-IF(M7="",0,M7)) | O7: ویزیتور پخش | P7: =IF(B7="","",VALUE(LEFT(B7,4))) | Q7: =IF(B7="","",VALUE(MID(B7,6,2)))
A8: =IF(B8="","",ROW()-3) | B8: 1405/06/05 | C8: فروشگاه رفاه خرم‌آباد | D8: خرم‌آباد | E8: لوبیا چیتی | F8: 10 | G8: 8 | H8: =IF(OR(F8="",G8=""),"",F8*G8) | I8: 980000 | J8: =IF(OR(G8="",I8=""),"",G8*I8) | K8: 0 | L8: =IF(J8="","",J8-IF(K8="",0,K8)) | M8: 7840000 | N8: =IF(L8="","",L8-IF(M8="",0,M8)) | O8: ویزیتور پخش | P8: =IF(B8="","",VALUE(LEFT(B8,4))) | Q8: =IF(B8="","",VALUE(MID(B8,6,2)))
A9: =IF(B9="","",ROW()-3) | B9: 1405/06/06 | C9: خواربار محمدی | D9: پلدختر | E9: عدس | F9: 0.4 | G9: 60 | H9: =IF(OR(F9="",G9=""),"",F9*G9) | I9: 43000 | J9: =IF(OR(G9="",I9=""),"",G9*I9) | K9: 0 | L9: =IF(J9="","",J9-IF(K9="",0,K9)) | M9: 2580000 | N9: =IF(L9="","",L9-IF(M9="",0,M9)) | O9: ویزیتور پخش | P9: =IF(B9="","",VALUE(LEFT(B9,4))) | Q9: =IF(B9="","",VALUE(MID(B9,6,2)))
A10: =IF(B10="","",ROW()-3) | B10: 1405/06/07 | C10: عمده‌فروشی حسینی | D10: کوهدشت | E10: نخود | F10: 10 | G10: 6 | H10: =IF(OR(F10="",G10=""),"",F10*G10) | I10: 720000 | J10: =IF(OR(G10="",I10=""),"",G10*I10) | K10: 200000 | L10: =IF(J10="","",J10-IF(K10="",0,K10)) | M10: 2500000 | N10: =IF(L10="","",L10-IF(M10="",0,M10)) | O10: ویزیتور پخش | P10: =IF(B10="","",VALUE(LEFT(B10,4))) | Q10: =IF(B10="","",VALUE(MID(B10,6,2)))
A11: =IF(B11="","",ROW()-3) | B11: 1405/06/08 | C11: مغازه میدان | D11: پلدختر | E11: لوبیا قرمز | F11: 0.4 | G11: 40 | H11: =IF(OR(F11="",G11=""),"",F11*G11) | I11: 44000 | J11: =IF(OR(G11="",I11=""),"",G11*I11) | K11: 0 | L11: =IF(J11="","",J11-IF(K11="",0,K11)) | M11: 1760000 | N11: =IF(L11="","",L11-IF(M11="",0,M11)) | O11: ویزیتور پخش | P11: =IF(B11="","",VALUE(LEFT(B11,4))) | Q11: =IF(B11="","",VALUE(MID(B11,6,2)))
A12: =IF(B12="","",ROW()-3) | B12: 1405/06/09 | C12: رستوران زاگرس | D12: خرم‌آباد | E12: عدس | F12: 0.9 | G12: 25 | H12: =IF(OR(F12="",G12=""),"",F12*G12) | I12: 88000 | J12: =IF(OR(G12="",I12=""),"",G12*I12) | K12: 0 | L12: =IF(J12="","",J12-IF(K12="",0,K12)) | M12: 0 | N12: =IF(L12="","",L12-IF(M12="",0,M12)) | O12: مدیر کارگاه | P12: =IF(B12="","",VALUE(LEFT(B12,4))) | Q12: =IF(B12="","",VALUE(MID(B12,6,2)))
A13: =IF(B13="","",ROW()-3) | B13: 1405/06/10 | C13: سوپر ستاره معمولان | D13: معمولان | E13: لوبیا چیتی | F13: 0.9 | G13: 35 | H13: =IF(OR(F13="",G13=""),"",F13*G13) | I13: 100000 | J13: =IF(OR(G13="",I13=""),"",G13*I13) | K13: 50000 | L13: =IF(J13="","",J13-IF(K13="",0,K13)) | M13: 2000000 | N13: =IF(L13="","",L13-IF(M13="",0,M13)) | O13: ویزیتور پخش | P13: =IF(B13="","",VALUE(LEFT(B13,4))) | Q13: =IF(B13="","",VALUE(MID(B13,6,2)))
A14: =IF(B14="","",ROW()-3) | B14: 1405/06/11 | C14: تعاونی مصرف فرهنگیان | D14: پلدختر | E14: لپه | F14: 0.9 | G14: 20 | H14: =IF(OR(F14="",G14=""),"",F14*G14) | I14: 92000 | J14: =IF(OR(G14="",I14=""),"",G14*I14) | K14: 0 | L14: =IF(J14="","",J14-IF(K14="",0,K14)) | M14: 1840000 | N14: =IF(L14="","",L14-IF(M14="",0,M14)) | O14: ویزیتور پخش | P14: =IF(B14="","",VALUE(LEFT(B14,4))) | Q14: =IF(B14="","",VALUE(MID(B14,6,2)))
A15: =IF(B15="","",ROW()-3) | B15: 1405/06/12 | C15: خواربار احمدی رومشکان | D15: رومشکان | E15: لوبیا قرمز | F15: 0.9 | G15: 28 | H15: =IF(OR(F15="",G15=""),"",F15*G15) | I15: 96000 | J15: =IF(OR(G15="",I15=""),"",G15*I15) | K15: 0 | L15: =IF(J15="","",J15-IF(K15="",0,K15)) | M15: 1500000 | N15: =IF(L15="","",L15-IF(M15="",0,M15)) | O15: ویزیتور پخش | P15: =IF(B15="","",VALUE(LEFT(B15,4))) | Q15: =IF(B15="","",VALUE(MID(B15,6,2)))
... A22: =IF(B22="","",ROW()-3) | B22: 1405/06/18 | C22: خواربار محمدی | D22: پلدختر | E22: ماش | F22: 0.4 | G22: 20 | H22: =IF(OR(F22="",G22=""),"",F22*G22) | I22: 40000 | J22: =IF(OR(G22="",I22=""),"",G22*I22) | K22: 0 | L22: =IF(J22="","",J22-IF(K22="",0,K22)) | M22: 800000 | N22: =IF(L22="","",L22-IF(M22="",0,M22)) | O22: ویزیتور پخش | P22: =IF(B22="","",VALUE(LEFT(B22,4))) | Q22: =IF(B22="","",VALUE(MID(B22,6,2)))
A23: =IF(B23="","",ROW()-3) | H23: =IF(OR(F23="",G23=""),"",F23*G23) | J23: =IF(OR(G23="",I23=""),"",G23*I23) | L23: =IF(J23="","",J23-IF(K23="",0,K23)) | N23: =IF(L23="","",L23-IF(M23="",0,M23)) | P23: =IF(B23="","",VALUE(LEFT(B23,4))) | Q23: =IF(B23="","",VALUE(MID(B23,6,2)))
A24: =IF(B24="","",ROW()-3) | H24: =IF(OR(F24="",G24=""),"",F24*G24) | J24: =IF(OR(G24="",I24=""),"",G24*I24) | L24: =IF(J24="","",J24-IF(K24="",0,K24)) | N24: =IF(L24="","",L24-IF(M24="",0,M24)) | P24: =IF(B24="","",VALUE(LEFT(B24,4))) | Q24: =IF(B24="","",VALUE(MID(B24,6,2)))
A25: =IF(B25="","",ROW()-3) | H25: =IF(OR(F25="",G25=""),"",F25*G25) | J25: =IF(OR(G25="",I25=""),"",G25*I25) | L25: =IF(J25="","",J25-IF(K25="",0,K25)) | N25: =IF(L25="","",L25-IF(M25="",0,M25)) | P25: =IF(B25="","",VALUE(LEFT(B25,4))) | Q25: =IF(B25="","",VALUE(MID(B25,6,2)))
A26: =IF(B26="","",ROW()-3) | H26: =IF(OR(F26="",G26=""),"",F26*G26) | J26: =IF(OR(G26="",I26=""),"",G26*I26) | L26: =IF(J26="","",J26-IF(K26="",0,K26)) | N26: =IF(L26="","",L26-IF(M26="",0,M26)) | P26: =IF(B26="","",VALUE(LEFT(B26,4))) | Q26: =IF(B26="","",VALUE(MID(B26,6,2)))
A27: =IF(B27="","",ROW()-3) | H27: =IF(OR(F27="",G27=""),"",F27*G27) | J27: =IF(OR(G27="",I27=""),"",G27*I27) | L27: =IF(J27="","",J27-IF(K27="",0,K27)) | N27: =IF(L27="","",L27-IF(M27="",0,M27)) | P27: =IF(B27="","",VALUE(LEFT(B27,4))) | Q27: =IF(B27="","",VALUE(MID(B27,6,2)))
A28: =IF(B28="","",ROW()-3) | H28: =IF(OR(F28="",G28=""),"",F28*G28) | J28: =IF(OR(G28="",I28=""),"",G28*I28) | L28: =IF(J28="","",J28-IF(K28="",0,K28)) | N28: =IF(L28="","",L28-IF(M28="",0,M28)) | P28: =IF(B28="","",VALUE(LEFT(B28,4))) | Q28: =IF(B28="","",VALUE(MID(B28,6,2)))
A29: =IF(B29="","",ROW()-3) | H29: =IF(OR(F29="",G29=""),"",F29*G29) | J29: =IF(OR(G29="",I29=""),"",G29*I29) | L29: =IF(J29="","",J29-IF(K29="",0,K29)) | N29: =IF(L29="","",L29-IF(M29="",0,M29)) | P29: =IF(B29="","",VALUE(LEFT(B29,4))) | Q29: =IF(B29="","",VALUE(MID(B29,6,2)))
A30: =IF(B30="","",ROW()-3) | H30: =IF(OR(F30="",G30=""),"",F30*G30) | J30: =IF(OR(G30="",I30=""),"",G30*I30) | L30: =IF(J30="","",J30-IF(K30="",0,K30)) | N30: =IF(L30="","",L30-IF(M30="",0,M30)) | P30: =IF(B30="","",VALUE(LEFT(B30,4))) | Q30: =IF(B30="","",VALUE(MID(B30,6,2)))
A31: =IF(B31="","",ROW()-3) | H31: =IF(OR(F31="",G31=""),"",F31*G31) | J31: =IF(OR(G31="",I31=""),"",G31*I31) | L31: =IF(J31="","",J31-IF(K31="",0,K31)) | N31: =IF(L31="","",L31-IF(M31="",0,M31)) | P31: =IF(B31="","",VALUE(LEFT(B31,4))) | Q31: =IF(B31="","",VALUE(MID(B31,6,2)))
A32: =IF(B32="","",ROW()-3) | H32: =IF(OR(F32="",G32=""),"",F32*G32) | J32: =IF(OR(G32="",I32=""),"",G32*I32) | L32: =IF(J32="","",J32-IF(K32="",0,K32)) | N32: =IF(L32="","",L32-IF(M32="",0,M32)) | P32: =IF(B32="","",VALUE(LEFT(B32,4))) | Q32: =IF(B32="","",VALUE(MID(B32,6,2)))
A33: =IF(B33="","",ROW()-3) | H33: =IF(OR(F33="",G33=""),"",F33*G33) | J33: =IF(OR(G33="",I33=""),"",G33*I33) | L33: =IF(J33="","",J33-IF(K33="",0,K33)) | N33: =IF(L33="","",L33-IF(M33="",0,M33)) | P33: =IF(B33="","",VALUE(LEFT(B33,4))) | Q33: =IF(B33="","",VALUE(MID(B33,6,2)))
A34: =IF(B34="","",ROW()-3) | H34: =IF(OR(F34="",G34=""),"",F34*G34) | J34: =IF(OR(G34="",I34=""),"",G34*I34) | L34: =IF(J34="","",J34-IF(K34="",0,K34)) | N34: =IF(L34="","",L34-IF(M34="",0,M34)) | P34: =IF(B34="","",VALUE(LEFT(B34,4))) | Q34: =IF(B34="","",VALUE(MID(B34,6,2)))
... A151: =IF(B151="","",ROW()-3) | H151: =IF(OR(F151="",G151=""),"",F151*G151) | J151: =IF(OR(G151="",I151=""),"",G151*I151) | L151: =IF(J151="","",J151-IF(K151="",0,K151)) | N151: =IF(L151="","",L151-IF(M151="",0,M151)) | P151: =IF(B151="","",VALUE(LEFT(B151,4))) | Q151: =IF(B151="","",VALUE(MID(B151,6,2)))

Sheet Customers
A1: دفتر مشتریان
A2: نام و مشخصات را وارد کنید. آخرین خرید، مجموع خرید و دسته A/B/C از روی برگه فروش خودکار پر می‌شود.
A3: نام مشتری | B3: شماره تماس | C3: شهر | D3: آدرس | E3: نوع مشتری | F3: آخرین ویزیت | G3: اولین خرید | H3: آخرین خرید | I3: مجموع خرید (تومان) | J3: دسته | K3: وضعیت | L3: توضیحات
A4: سوپرمارکت رضایی | B4: 0916-111-2201 | C4: پلدختر | D4: خیابان امام، پلاک ۱۲ | E4: سوپرمارکت | F4: 1405/06/04 | G4: =IF(A4="","",IFERROR(MINIFS(Sales!$B$4:$B$151,Sales!$C$4:$C$151,A4),"—")) | H4: =IF(A4="","",IFERROR(MAXIFS(Sales!$B$4:$B$151,Sales!$C$4:$C$151,A4),"—")) | I4: =IF(A4="","",SUMIF(Sales!$C$4:$C$151,A4,Sales!$L$4:$L$151)) | J4: =IF(OR(A4="",I4=""),"",IF(I4>=تنظیمات!$B$10,"A",IF(I4>=تنظیمات!$B$11,"B","C"))) | K4: فعال | L4: مشتری ثابت هفتگی
A5: خواربار محمدی | B5: 0916-222-3302 | C5: پلدختر | D5: بازار روز، دهنه ۳ | E5: خرده‌فروش | F5: 1405/06/17 | G5: =IF(A5="","",IFERROR(MINIFS(Sales!$B$4:$B$151,Sales!$C$4:$C$151,A5),"—")) | H5: =IF(A5="","",IFERROR(MAXIFS(Sales!$B$4:$B$151,Sales!$C$4:$C$151,A5),"—")) | I5: =IF(A5="","",SUMIF(Sales!$C$4:$C$151,A5,Sales!$L$4:$L$151)) | J5: =IF(OR(A5="",I5=""),"",IF(I5>=تنظیمات!$B$10,"A",IF(I5>=تنظیمات!$B$11,"B","C"))) | K5: فعال
A6: فروشگاه رفاه خرم‌آباد | B6: 0916-333-4403 | C6: خرم‌آباد | D6: بلوار شریعتی | E6: سوپرمارکت | F6: 1405/06/15 | G6: =IF(A6="","",IFERROR(MINIFS(Sales!$B$4:$B$151,Sales!$C$4:$C$151,A6),"—")) | H6: =IF(A6="","",IFERROR(MAXIFS(Sales!$B$4:$B$151,Sales!$C$4:$C$151,A6),"—")) | I6: =IF(A6="","",SUMIF(Sales!$C$4:$C$151,A6,Sales!$L$4:$L$151)) | J6: =IF(OR(A6="",I6=""),"",IF(I6>=تنظیمات!$B$10,"A",IF(I6>=تنظیمات!$B$11,"B","C"))) | K6: فعال | L6: سفارش عمده
A7: عمده‌فروشی حسینی | B7: 0916-444-5504 | C7: کوهدشت | D7: جاده پلدختر | E7: عمده‌فروش | F7: 1405/06/13 | G7: =IF(A7="","",IFERROR(MINIFS(Sales!$B$4:$B$151,Sales!$C$4:$C$151,A7),"—")) | H7: =IF(A7="","",IFERROR(MAXIFS(Sales!$B$4:$B$151,Sales!$C$4:$C$151,A7),"—")) | I7: =IF(A7="","",SUMIF(Sales!$C$4:$C$151,A7,Sales!$L$4:$L$151)) | J7: =IF(OR(A7="",I7=""),"",IF(I7>=تنظیمات!$B$10,"A",IF(I7>=تنظیمات!$B$11,"B","C"))) | K7: فعال | L7: پرداخت نسیه — پیگیری وصول
A8: مغازه میدان | B8: 0916-555-6605 | C8: پلدختر | D8: میدان مرکزی | E8: خرده‌فروش | F8: 1405/06/17 | G8: =IF(A8="","",IFERROR(MINIFS(Sales!$B$4:$B$151,Sales!$C$4:$C$151,A8),"—")) | H8: =IF(A8="","",IFERROR(MAXIFS(Sales!$B$4:$B$151,Sales!$C$4:$C$151,A8),"—")) | I8: =IF(A8="","",SUMIF(Sales!$C$4:$C$151,A8,Sales!$L$4:$L$151)) | J8: =IF(OR(A8="",I8=""),"",IF(I8>=تنظیمات!$B$10,"A",IF(I8>=تنظیمات!$B$11,"B","C"))) | K8: فعال
A9: رستوران زاگرس | B9: 0916-666-7706 | C9: خرم‌آباد | D9: بلوار ولایت | E9: رستوران | F9: 1405/06/09 | G9: =IF(A9="","",IFERROR(MINIFS(Sales!$B$4:$B$151,Sales!$C$4:$C$151,A9),"—")) | H9: =IF(A9="","",IFERROR(MAXIFS(Sales!$B$4:$B$151,Sales!$C$4:$C$151,A9),"—")) | I9: =IF(A9="","",SUMIF(Sales!$C$4:$C$151,A9,Sales!$L$4:$L$151)) | J9: =IF(OR(A9="",I9=""),"",IF(I9>=تنظیمات!$B$10,"A",IF(I9>=تنظیمات!$B$11,"B","C"))) | K9: فعال | L9: مشتری جدید — هنوز وصول نشده
A10: سوپر ستاره معمولان | B10: 0916-777-8807 | C10: معمولان | D10: خیابان اصلی | E10: سوپرمارکت | F10: 1405/06/18 | G10: =IF(A10="","",IFERROR(MINIFS(Sales!$B$4:$B$151,Sales!$C$4:$C$151,A10),"—")) | H10: =IF(A10="","",IFERROR(MAXIFS(Sales!$B$4:$B$151,Sales!$C$4:$C$151,A10),"—")) | I10: =IF(A10="","",SUMIF(Sales!$C$4:$C$151,A10,Sales!$L$4:$L$151)) | J10: =IF(OR(A10="",I10=""),"",IF(I10>=تنظیمات!$B$10,"A",IF(I10>=تنظیمات!$B$11,"B","C"))) | K10: فعال | L10: مشتری جدید
A11: تعاونی مصرف فرهنگیان | B11: 0916-888-9908 | C11: پلدختر | D11: نزدیک آموزش و پرورش | E11: خرده‌فروش | F11: 1405/06/11 | G11: =IF(A11="","",IFERROR(MINIFS(Sales!$B$4:$B$151,Sales!$C$4:$C$151,A11),"—")) | H11: =IF(A11="","",IFERROR(MAXIFS(Sales!$B$4:$B$151,Sales!$C$4:$C$151,A11),"—")) | I11: =IF(A11="","",SUMIF(Sales!$C$4:$C$151,A11,Sales!$L$4:$L$151)) | J11: =IF(OR(A11="",I11=""),"",IF(I11>=تنظیمات!$B$10,"A",IF(I11>=تنظیمات!$B$11,"B","C"))) | K11: فعال
A12: خواربار احمدی رومشکان | B12: 0916-999-1010 | C12: رومشکان | D12: بازار رومشکان | E12: خرده‌فروش | F12: 1405/06/12 | G12: =IF(A12="","",IFERROR(MINIFS(Sales!$B$4:$B$151,Sales!$C$4:$C$151,A12),"—")) | H12: =IF(A12="","",IFERROR(MAXIFS(Sales!$B$4:$B$151,Sales!$C$4:$C$151,A12),"—")) | I12: =IF(A12="","",SUMIF(Sales!$C$4:$C$151,A12,Sales!$L$4:$L$151)) | J12: =IF(OR(A12="",I12=""),"",IF(I12>=تنظیمات!$B$10,"A",IF(I12>=تنظیمات!$B$11,"B","C"))) | K12: فعال | L12: مشتری جدید
A13: پخش مواد غذایی کرمی | B13: 0916-101-1212 | C13: اندیمشک | D13: جاده اندیمشک | E13: عمده‌فروش | F13: 1405/06/16 | G13: =IF(A13="","",IFERROR(MINIFS(Sales!$B$4:$B$151,Sales!$C$4:$C$151,A13),"—")) | H13: =IF(A13="","",IFERROR(MAXIFS(Sales!$B$4:$B$151,Sales!$C$4:$C$151,A13),"—")) | I13: =IF(A13="","",SUMIF(Sales!$C$4:$C$151,A13,Sales!$L$4:$L$151)) | J13: =IF(OR(A13="",I13=""),"",IF(I13>=تنظیمات!$B$10,"A",IF(I13>=تنظیمات!$B$11,"B","C"))) | K13: فعال | L13: مسیر جدید ویزیت
A14: سوپر امید کوهدشت | B14: 0916-131-1414 | C14: کوهدشت | D14: فلکه مرکزی | E14: سوپرمارکت | F14: 1405/05/10 | G14: =IF(A14="","",IFERROR(MINIFS(Sales!$B$4:$B$151,Sales!$C$4:$C$151,A14),"—")) | H14: =IF(A14="","",IFERROR(MAXIFS(Sales!$B$4:$B$151,Sales!$C$4:$C$151,A14),"—")) | I14: =IF(A14="","",SUMIF(Sales!$C$4:$C$151,A14,Sales!$L$4:$L$151)) | J14: =IF(OR(A14="",I14=""),"",IF(I14>=تنظیمات!$B$10,"A",IF(I14>=تنظیمات!$B$11,"B","C"))) | K14: بالقوه | L14: ویزیت شده، هنوز خرید نکرده
A15: خواربار روستایی چم مهر | B15: 0916-151-1616 | C15: پلدختر | D15: چم مهر | E15: خرده‌فروش | G15: =IF(A15="","",IFERROR(MINIFS(Sales!$B$4:$B$151,Sales!$C$4:$C$151,A15),"—")) | H15: =IF(A15="","",IFERROR(MAXIFS(Sales!$B$4:$B$151,Sales!$C$4:$C$151,A15),"—")) | I15: =IF(A15="","",SUMIF(Sales!$C$4:$C$151,A15,Sales!$L$4:$L$151)) | J15: =IF(OR(A15="",I15=""),"",IF(I15>=تنظیمات!$B$10,"A",IF(I15>=تنظیمات!$B$11,"B","C"))) | K15: بالقوه | L15: در برنامه ویزیت هفته بعد
G16: =IF(A16="","",IFERROR(MINIFS(Sales!$B$4:$B$151,Sales!$C$4:$C$151,A16),"—")) | H16: =IF(A16="","",IFERROR(MAXIFS(Sales!$B$4:$B$151,Sales!$C$4:$C$151,A16),"—")) | I16: =IF(A16="","",SUMIF(Sales!$C$4:$C$151,A16,Sales!$L$4:$L$151)) | J16: =IF(OR(A16="",I16=""),"",IF(I16>=تنظیمات!$B$10,"A",IF(I16>=تنظیمات!$B$11,"B","C")))
G17: =IF(A17="","",IFERROR(MINIFS(Sales!$B$4:$B$151,Sales!$C$4:$C$151,A17),"—")) | H17: =IF(A17="","",IFERROR(MAXIFS(Sales!$B$4:$B$151,Sales!$C$4:$C$151,A17),"—")) | I17: =IF(A17="","",SUMIF(Sales!$C$4:$C$151,A17,Sales!$L$4:$L$151)) | J17: =IF(OR(A17="",I17=""),"",IF(I17>=تنظیمات!$B$10,"A",IF(I17>=تنظیمات!$B$11,"B","C")))
G18: =IF(A18="","",IFERROR(MINIFS(Sales!$B$4:$B$151,Sales!$C$4:$C$151,A18),"—")) | H18: =IF(A18="","",IFERROR(MAXIFS(Sales!$B$4:$B$151,Sales!$C$4:$C$151,A18),"—")) | I18: =IF(A18="","",SUMIF(Sales!$C$4:$C$151,A18,Sales!$L$4:$L$151)) | J18: =IF(OR(A18="",I18=""),"",IF(I18>=تنظیمات!$B$10,"A",IF(I18>=تنظیمات!$B$11,"B","C")))
G19: =IF(A19="","",IFERROR(MINIFS(Sales!$B$4:$B$151,Sales!$C$4:$C$151,A19),"—")) | H19: =IF(A19="","",IFERROR(MAXIFS(Sales!$B$4:$B$151,Sales!$C$4:$C$151,A19),"—")) | I19: =IF(A19="","",SUMIF(Sales!$C$4:$C$151,A19,Sales!$L$4:$L$151)) | J19: =IF(OR(A19="",I19=""),"",IF(I19>=تنظیمات!$B$10,"A",IF(I19>=تنظیمات!$B$11,"B","C")))
G20: =IF(A20="","",IFERROR(MINIFS(Sales!$B$4:$B$151,Sales!$C$4:$C$151,A20),"—")) | H20: =IF(A20="","",IFERROR(MAXIFS(Sales!$B$4:$B$151,Sales!$C$4:$C$151,A20),"—")) | I20: =IF(A20="","",SUMIF(Sales!$C$4:$C$151,A20,Sales!$L$4:$L$151)) | J20: =IF(OR(A20="",I20=""),"",IF(I20>=تنظیمات!$B$10,"A",IF(I20>=تنظیمات!$B$11,"B","C")))
G21: =IF(A21="","",IFERROR(MINIFS(Sales!$B$4:$B$151,Sales!$C$4:$C$151,A21),"—")) | H21: =IF(A21="","",IFERROR(MAXIFS(Sales!$B$4:$B$151,Sales!$C$4:$C$151,A21),"—")) | I21: =IF(A21="","",SUMIF(Sales!$C$4:$C$151,A21,Sales!$L$4:$L$151)) | J21: =IF(OR(A21="",I21=""),"",IF(I21>=تنظیمات!$B$10,"A",IF(I21>=تنظیمات!$B$11,"B","C")))
G22: =IF(A22="","",IFERROR(MINIFS(Sales!$B$4:$B$151,Sales!$C$4:$C$151,A22),"—")) | H22: =IF(A22="","",IFERROR(MAXIFS(Sales!$B$4:$B$151,Sales!$C$4:$C$151,A22),"—")) | I22: =IF(A22="","",SUMIF(Sales!$C$4:$C$151,A22,Sales!$L$4:$L$151)) | J22: =IF(OR(A22="",I22=""),"",IF(I22>=تنظیمات!$B$10,"A",IF(I22>=تنظیمات!$B$11,"B","C")))
G23: =IF(A23="","",IFERROR(MINIFS(Sales!$B$4:$B$151,Sales!$C$4:$C$151,A23),"—")) | H23: =IF(A23="","",IFERROR(MAXIFS(Sales!$B$4:$B$151,Sales!$C$4:$C$151,A23),"—")) | I23: =IF(A23="","",SUMIF(Sales!$C$4:$C$151,A23,Sales!$L$4:$L$151)) | J23: =IF(OR(A23="",I23=""),"",IF(I23>=تنظیمات!$B$10,"A",IF(I23>=تنظیمات!$B$11,"B","C")))
G24: =IF(A24="","",IFERROR(MINIFS(Sales!$B$4:$B$151,Sales!$C$4:$C$151,A24),"—")) | H24: =IF(A24="","",IFERROR(MAXIFS(Sales!$B$4:$B$151,Sales!$C$4:$C$151,A24),"—")) | I24: =IF(A24="","",SUMIF(Sales!$C$4:$C$151,A24,Sales!$L$4:$L$151)) | J24: =IF(OR(A24="",I24=""),"",IF(I24>=تنظیمات!$B$10,"A",IF(I24>=تنظیمات!$B$11,"B","C")))
G25: =IF(A25="","",IFERROR(MINIFS(Sales!$B$4:$B$151,Sales!$C$4:$C$151,A25),"—")) | H25: =IF(A25="","",IFERROR(MAXIFS(Sales!$B$4:$B$151,Sales!$C$4:$C$151,A25),"—")) | I25: =IF(A25="","",SUMIF(Sales!$C$4:$C$151,A25,Sales!$L$4:$L$151)) | J25: =IF(OR(A25="",I25=""),"",IF(I25>=تنظیمات!$B$10,"A",IF(I25>=تنظیمات!$B$11,"B","C")))
G26: =IF(A26="","",IFERROR(MINIFS(Sales!$B$4:$B$151,Sales!$C$4:$C$151,A26),"—")) | H26: =IF(A26="","",IFERROR(MAXIFS(Sales!$B$4:$B$151,Sales!$C$4:$C$151,A26),"—")) | I26: =IF(A26="","",SUMIF(Sales!$C$4:$C$151,A26,Sales!$L$4:$L$151)) | J26: =IF(OR(A26="",I26=""),"",IF(I26>=تنظیمات!$B$10,"A",IF(I26>=تنظیمات!$B$11,"B","C")))
G27: =IF(A27="","",IFERROR(MINIFS(Sales!$B$4:$B$151,Sales!$C$4:$C$151,A27),"—")) | H27: =IF(A27="","",IFERROR(MAXIFS(Sales!$B$4:$B$151,Sales!$C$4:$C$151,A27),"—")) | I27: =IF(A27="","",SUMIF(Sales!$C$4:$C$151,A27,Sales!$L$4:$L$151)) | J27: =IF(OR(A27="",I27=""),"",IF(I27>=تنظیمات!$B$10,"A",IF(I27>=تنظیمات!$B$11,"B","C")))
... G151: =IF(A151="","",IFERROR(MINIFS(Sales!$B$4:$B$151,Sales!$C$4:$C$151,A151),"—")) | H151: =IF(A151="","",IFERROR(MAXIFS(Sales!$B$4:$B$151,Sales!$C$4:$C$151,A151),"—")) | I151: =IF(A151="","",SUMIF(Sales!$C$4:$C$151,A151,Sales!$L$4:$L$151)) | J151: =IF(OR(A151="",I151=""),"",IF(I151>=تنظیمات!$B$10,"A",IF(I151>=تنظیمات!$B$11,"B","C")))

Sheet SalesRep
A1: گزارش ویزیتور / پخش
A2: درصد انجام ویزیت و نرخ تبدیل خودکار است. هر روز یک ردیف — از روی فرم کاغذی ویزیتور.
A3: ردیف | B3: تاریخ شمسی | C3: منطقه | D3: برنامه‌ریزی‌شده | E3: ویزیت‌شده | F3: سفارش گرفته‌شده | G3: مبلغ سفارش | H3: مشتری جدید | I3: مبلغ وصول‌شده | J3: کیلومتر | K3: هزینه سوخت | L3: توضیحات | M3: درصد انجام ویزیت | N3: نرخ تبدیل | O3: سال | P3: ماه
A4: =IF(B4="","",ROW()-3) | B4: 1405/06/04 | C4: پلدختر شهر | D4: 8 | E4: 7 | F4: 3 | G4: 7140000 | H4: 0 | I4: 6060000 | J4: 42 | K4: 420000 | M4: =IF(OR(D4="",D4=0),"",E4/D4) | N4: =IF(OR(E4="",E4=0),"",F4/E4) | O4: =IF(B4="","",VALUE(LEFT(B4,4))) | P4: =IF(B4="","",VALUE(MID(B4,6,2)))
A5: =IF(B5="","",ROW()-3) | B5: 1405/06/05 | C5: خرم‌آباد | D5: 6 | E5: 5 | F5: 1 | G5: 7840000 | H5: 0 | I5: 7840000 | J5: 118 | K5: 1100000 | M5: =IF(OR(D5="",D5=0),"",E5/D5) | N5: =IF(OR(E5="",E5=0),"",F5/E5) | O5: =IF(B5="","",VALUE(LEFT(B5,4))) | P5: =IF(B5="","",VALUE(MID(B5,6,2)))
A6: =IF(B6="","",ROW()-3) | B6: 1405/06/07 | C6: کوهدشت | D6: 7 | E6: 6 | F6: 1 | G6: 4120000 | H6: 0 | I6: 2500000 | J6: 95 | K6: 900000 | L6: یکی از مشتری‌ها نبود | M6: =IF(OR(D6="",D6=0),"",E6/D6) | N6: =IF(OR(E6="",E6=0),"",F6/E6) | O6: =IF(B6="","",VALUE(LEFT(B6,4))) | P6: =IF(B6="","",VALUE(MID(B6,6,2)))
A7: =IF(B7="","",ROW()-3) | B7: 1405/06/08 | C7: پلدختر شهر | D7: 6 | E7: 6 | F7: 2 | G7: 1760000 | H7: 0 | I7: 1760000 | J7: 38 | K7: 380000 | M7: =IF(OR(D7="",D7=0),"",E7/D7) | N7: =IF(OR(E7="",E7=0),"",F7/E7) | O7: =IF(B7="","",VALUE(LEFT(B7,4))) | P7: =IF(B7="","",VALUE(MID(B7,6,2)))
A8: =IF(B8="","",ROW()-3) | B8: 1405/06/09 | C8: خرم‌آباد | D8: 5 | E8: 4 | F8: 1 | G8: 2200000 | H8: 1 | I8: 0 | J8: 120 | K8: 1150000 | L8: رستوران زاگرس مشتری جدید | M8: =IF(OR(D8="",D8=0),"",E8/D8) | N8: =IF(OR(E8="",E8=0),"",F8/E8) | O8: =IF(B8="","",VALUE(LEFT(B8,4))) | P8: =IF(B8="","",VALUE(MID(B8,6,2)))
A9: =IF(B9="","",ROW()-3) | B9: 1405/06/10 | C9: معمولان | D9: 5 | E9: 4 | F9: 1 | G9: 3450000 | H9: 1 | I9: 2000000 | J9: 55 | K9: 520000 | M9: =IF(OR(D9="",D9=0),"",E9/D9) | N9: =IF(OR(E9="",E9=0),"",F9/E9) | O9: =IF(B9="","",VALUE(LEFT(B9,4))) | P9: =IF(B9="","",VALUE(MID(B9,6,2)))
A10: =IF(B10="","",ROW()-3) | B10: 1405/06/11 | C10: پلدختر شهر | D10: 6 | E10: 5 | F10: 1 | G10: 1840000 | H10: 0 | I10: 1840000 | J10: 40 | K10: 400000 | M10: =IF(OR(D10="",D10=0),"",E10/D10) | N10: =IF(OR(E10="",E10=0),"",F10/E10) | O10: =IF(B10="","",VALUE(LEFT(B10,4))) | P10: =IF(B10="","",VALUE(MID(B10,6,2)))
A11: =IF(B11="","",ROW()-3) | B11: 1405/06/12 | C11: رومشکان | D11: 5 | E11: 3 | F11: 1 | G11: 2688000 | H11: 1 | I11: 1500000 | J11: 70 | K11: 680000 | L11: جاده خراب — ۳ ویزیت جا ماند | M11: =IF(OR(D11="",D11=0),"",E11/D11) | N11: =IF(OR(E11="",E11=0),"",F11/E11) | O11: =IF(B11="","",VALUE(LEFT(B11,4))) | P11: =IF(B11="","",VALUE(MID(B11,6,2)))
A12: =IF(B12="","",ROW()-3) | B12: 1405/06/13 | C12: کوهدشت | D12: 6 | E12: 5 | F12: 1 | G12: 4950000 | H12: 0 | I12: 0 | J12: 98 | K12: 940000 | L12: عمده‌فروشی نسیه گرفت | M12: =IF(OR(D12="",D12=0),"",E12/D12) | N12: =IF(OR(E12="",E12=0),"",F12/E12) | O12: =IF(B12="","",VALUE(LEFT(B12,4))) | P12: =IF(B12="","",VALUE(MID(B12,6,2)))
A13: =IF(B13="","",ROW()-3) | B13: 1405/06/14 | C13: پلدختر شهر | D13: 5 | E13: 5 | F13: 1 | G13: 2115000 | H13: 0 | I13: 2115000 | J13: 35 | K13: 350000 | M13: =IF(OR(D13="",D13=0),"",E13/D13) | N13: =IF(OR(E13="",E13=0),"",F13/E13) | O13: =IF(B13="","",VALUE(LEFT(B13,4))) | P13: =IF(B13="","",VALUE(MID(B13,6,2)))
A14: =IF(B14="","",ROW()-3) | B14: 1405/06/15 | C14: خرم‌آباد | D14: 6 | E14: 5 | F14: 1 | G14: 3260000 | H14: 0 | I14: 2000000 | J14: 122 | K14: 1180000 | M14: =IF(OR(D14="",D14=0),"",E14/D14) | N14: =IF(OR(E14="",E14=0),"",F14/E14) | O14: =IF(B14="","",VALUE(LEFT(B14,4))) | P14: =IF(B14="","",VALUE(MID(B14,6,2)))
A15: =IF(B15="","",ROW()-3) | B15: 1405/06/16 | C15: اندیمشک | D15: 4 | E15: 3 | F15: 1 | G15: 4950000 | H15: 1 | I15: 3000000 | J15: 145 | K15: 1400000 | L15: مسیر جدید | M15: =IF(OR(D15="",D15=0),"",E15/D15) | N15: =IF(OR(E15="",E15=0),"",F15/E15) | O15: =IF(B15="","",VALUE(LEFT(B15,4))) | P15: =IF(B15="","",VALUE(MID(B15,6,2)))
A16: =IF(B16="","",ROW()-3) | B16: 1405/06/17 | C16: پلدختر شهر | D16: 7 | E16: 6 | F16: 2 | G16: 2305000 | H16: 0 | I16: 2305000 | J16: 44 | K16: 440000 | M16: =IF(OR(D16="",D16=0),"",E16/D16) | N16: =IF(OR(E16="",E16=0),"",F16/E16) | O16: =IF(B16="","",VALUE(LEFT(B16,4))) | P16: =IF(B16="","",VALUE(MID(B16,6,2)))
A17: =IF(B17="","",ROW()-3) | B17: 1405/06/18 | C17: معمولان | D17: 5 | E17: 4 | F17: 1 | G17: 1674000 | H17: 0 | I17: 800000 | J17: 58 | K17: 550000 | M17: =IF(OR(D17="",D17=0),"",E17/D17) | N17: =IF(OR(E17="",E17=0),"",F17/E17) | O17: =IF(B17="","",VALUE(LEFT(B17,4))) | P17: =IF(B17="","",VALUE(MID(B17,6,2)))
A18: =IF(B18="","",ROW()-3) | M18: =IF(OR(D18="",D18=0),"",E18/D18) | N18: =IF(OR(E18="",E18=0),"",F18/E18) | O18: =IF(B18="","",VALUE(LEFT(B18,4))) | P18: =IF(B18="","",VALUE(MID(B18,6,2)))
A19: =IF(B19="","",ROW()-3) | M19: =IF(OR(D19="",D19=0),"",E19/D19) | N19: =IF(OR(E19="",E19=0),"",F19/E19) | O19: =IF(B19="","",VALUE(LEFT(B19,4))) | P19: =IF(B19="","",VALUE(MID(B19,6,2)))
A20: =IF(B20="","",ROW()-3) | M20: =IF(OR(D20="",D20=0),"",E20/D20) | N20: =IF(OR(E20="",E20=0),"",F20/E20) | O20: =IF(B20="","",VALUE(LEFT(B20,4))) | P20: =IF(B20="","",VALUE(MID(B20,6,2)))
A21: =IF(B21="","",ROW()-3) | M21: =IF(OR(D21="",D21=0),"",E21/D21) | N21: =IF(OR(E21="",E21=0),"",F21/E21) | O21: =IF(B21="","",VALUE(LEFT(B21,4))) | P21: =IF(B21="","",VALUE(MID(B21,6,2)))
A22: =IF(B22="","",ROW()-3) | M22: =IF(OR(D22="",D22=0),"",E22/D22) | N22: =IF(OR(E22="",E22=0),"",F22/E22) | O22: =IF(B22="","",VALUE(LEFT(B22,4))) | P22: =IF(B22="","",VALUE(MID(B22,6,2)))
A23: =IF(B23="","",ROW()-3) | M23: =IF(OR(D23="",D23=0),"",E23/D23) | N23: =IF(OR(E23="",E23=0),"",F23/E23) | O23: =IF(B23="","",VALUE(LEFT(B23,4))) | P23: =IF(B23="","",VALUE(MID(B23,6,2)))
A24: =IF(B24="","",ROW()-3) | M24: =IF(OR(D24="",D24=0),"",E24/D24) | N24: =IF(OR(E24="",E24=0),"",F24/E24) | O24: =IF(B24="","",VALUE(LEFT(B24,4))) | P24: =IF(B24="","",VALUE(MID(B24,6,2)))
A25: =IF(B25="","",ROW()-3) | M25: =IF(OR(D25="",D25=0),"",E25/D25) | N25: =IF(OR(E25="",E25=0),"",F25/E25) | O25: =IF(B25="","",VALUE(LEFT(B25,4))) | P25: =IF(B25="","",VALUE(MID(B25,6,2)))
A26: =IF(B26="","",ROW()-3) | M26: =IF(OR(D26="",D26=0),"",E26/D26) | N26: =IF(OR(E26="",E26=0),"",F26/E26) | O26: =IF(B26="","",VALUE(LEFT(B26,4))) | P26: =IF(B26="","",VALUE(MID(B26,6,2)))
A27: =IF(B27="","",ROW()-3) | M27: =IF(OR(D27="",D27=0),"",E27/D27) | N27: =IF(OR(E27="",E27=0),"",F27/E27) | O27: =IF(B27="","",VALUE(LEFT(B27,4))) | P27: =IF(B27="","",VALUE(MID(B27,6,2)))
A28: =IF(B28="","",ROW()-3) | M28: =IF(OR(D28="",D28=0),"",E28/D28) | N28: =IF(OR(E28="",E28=0),"",F28/E28) | O28: =IF(B28="","",VALUE(LEFT(B28,4))) | P28: =IF(B28="","",VALUE(MID(B28,6,2)))
A29: =IF(B29="","",ROW()-3) | M29: =IF(OR(D29="",D29=0),"",E29/D29) | N29: =IF(OR(E29="",E29=0),"",F29/E29) | O29: =IF(B29="","",VALUE(LEFT(B29,4))) | P29: =IF(B29="","",VALUE(MID(B29,6,2)))
... A151: =IF(B151="","",ROW()-3) | M151: =IF(OR(D151="",D151=0),"",E151/D151) | N151: =IF(OR(E151="",E151=0),"",F151/E151) | O151: =IF(B151="","",VALUE(LEFT(B151,4))) | P151: =IF(B151="","",VALUE(MID(B151,6,2)))

Sheet Expenses
A1: هزینه‌ها
A2: هر هزینه یک ردیف. حقوق ماهانه را اول ماه بزنید. سوخت ماشین پخش جدا از برگه ویزیتور هم اینجا جمع می‌شود اگر وارد کنید.
A3: ردیف | B3: تاریخ شمسی | C3: نوع هزینه | D3: مبلغ (تومان) | E3: پرداخت‌کننده | F3: روش پرداخت | G3: توضیحات | H3: سال | I3: ماه
A4: =IF(B4="","",ROW()-3) | B4: 1405/06/01 | C4: اجاره | D4: 4000000 | E4: مدیر کارگاه | F4: نقد | G4: اجاره سوله شهریور | H4: =IF(B4="","",VALUE(LEFT(B4,4))) | I4: =IF(B4="","",VALUE(MID(B4,6,2)))
A5: =IF(B5="","",ROW()-3) | B5: 1405/06/01 | C5: حقوق | D5: 18000000 | E5: مدیر کارگاه | F5: نقد | G5: حقوق مدیر | H5: =IF(B5="","",VALUE(LEFT(B5,4))) | I5: =IF(B5="","",VALUE(MID(B5,6,2)))
A6: =IF(B6="","",ROW()-3) | B6: 1405/06/01 | C6: حقوق | D6: 8000000 | E6: مدیر کارگاه | F6: نقد | G6: حقوق مسئول انبار | H6: =IF(B6="","",VALUE(LEFT(B6,4))) | I6: =IF(B6="","",VALUE(MID(B6,6,2)))
A7: =IF(B7="","",ROW()-3) | B7: 1405/06/01 | C7: حقوق | D7: 9000000 | E7: مدیر کارگاه | F7: نقد | G7: حقوق بسته‌بندی | H7: =IF(B7="","",VALUE(LEFT(B7,4))) | I7: =IF(B7="","",VALUE(MID(B7,6,2)))
A8: =IF(B8="","",ROW()-3) | B8: 1405/06/01 | C8: حقوق | D8: 10000000 | E8: مدیر کارگاه | F8: نقد | G8: حقوق ویزیتور — بدون پورسانت | H8: =IF(B8="","",VALUE(LEFT(B8,4))) | I8: =IF(B8="","",VALUE(MID(B8,6,2)))
A9: =IF(B9="","",ROW()-3) | B9: 1405/06/05 | C9: برق | D9: 1800000 | E9: پدر مدیر | F9: کارت | G9: قبض برق | H9: =IF(B9="","",VALUE(LEFT(B9,4))) | I9: =IF(B9="","",VALUE(MID(B9,6,2)))
A10: =IF(B10="","",ROW()-3) | B10: 1405/06/08 | C10: بسته‌بندی | D10: 3200000 | E10: مدیر کارگاه | F10: نقد | G10: نایلون و کارتن | H10: =IF(B10="","",VALUE(LEFT(B10,4))) | I10: =IF(B10="","",VALUE(MID(B10,6,2)))
A11: =IF(B11="","",ROW()-3) | B11: 1405/06/12 | C11: تعمیرات | D11: 750000 | E11: پدر مدیر | F11: نقد | G11: تنظیم ترازو | H11: =IF(B11="","",VALUE(LEFT(B11,4))) | I11: =IF(B11="","",VALUE(MID(B11,6,2)))
A12: =IF(B12="","",ROW()-3) | B12: 1405/06/15 | C12: گاز | D12: 600000 | E12: پدر مدیر | F12: کارت | H12: =IF(B12="","",VALUE(LEFT(B12,4))) | I12: =IF(B12="","",VALUE(MID(B12,6,2)))
A13: =IF(B13="","",ROW()-3) | B13: 1405/06/16 | C13: سوخت | D13: 1400000 | E13: ویزیتور پخش | F13: نقد | G13: باک ماشین پخش | H13: =IF(B13="","",VALUE(LEFT(B13,4))) | I13: =IF(B13="","",VALUE(MID(B13,6,2)))
A14: =IF(B14="","",ROW()-3) | B14: 1405/06/18 | C14: آب | D14: 250000 | E14: پدر مدیر | F14: کارت | H14: =IF(B14="","",VALUE(LEFT(B14,4))) | I14: =IF(B14="","",VALUE(MID(B14,6,2)))
A15: =IF(B15="","",ROW()-3) | H15: =IF(B15="","",VALUE(LEFT(B15,4))) | I15: =IF(B15="","",VALUE(MID(B15,6,2)))
A16: =IF(B16="","",ROW()-3) | H16: =IF(B16="","",VALUE(LEFT(B16,4))) | I16: =IF(B16="","",VALUE(MID(B16,6,2)))
A17: =IF(B17="","",ROW()-3) | H17: =IF(B17="","",VALUE(LEFT(B17,4))) | I17: =IF(B17="","",VALUE(MID(B17,6,2)))
A18: =IF(B18="","",ROW()-3) | H18: =IF(B18="","",VALUE(LEFT(B18,4))) | I18: =IF(B18="","",VALUE(MID(B18,6,2)))
A19: =IF(B19="","",ROW()-3) | H19: =IF(B19="","",VALUE(LEFT(B19,4))) | I19: =IF(B19="","",VALUE(MID(B19,6,2)))
A20: =IF(B20="","",ROW()-3) | H20: =IF(B20="","",VALUE(LEFT(B20,4))) | I20: =IF(B20="","",VALUE(MID(B20,6,2)))
A21: =IF(B21="","",ROW()-3) | H21: =IF(B21="","",VALUE(LEFT(B21,4))) | I21: =IF(B21="","",VALUE(MID(B21,6,2)))
A22: =IF(B22="","",ROW()-3) | H22: =IF(B22="","",VALUE(LEFT(B22,4))) | I22: =IF(B22="","",VALUE(MID(B22,6,2)))
A23: =IF(B23="","",ROW()-3) | H23: =IF(B23="","",VALUE(LEFT(B23,4))) | I23: =IF(B23="","",VALUE(MID(B23,6,2)))
A24: =IF(B24="","",ROW()-3) | H24: =IF(B24="","",VALUE(LEFT(B24,4))) | I24: =IF(B24="","",VALUE(MID(B24,6,2)))
A25: =IF(B25="","",ROW()-3) | H25: =IF(B25="","",VALUE(LEFT(B25,4))) | I25: =IF(B25="","",VALUE(MID(B25,6,2)))
A26: =IF(B26="","",ROW()-3) | H26: =IF(B26="","",VALUE(LEFT(B26,4))) | I26: =IF(B26="","",VALUE(MID(B26,6,2)))
... A151: =IF(B151="","",ROW()-3) | H151: =IF(B151="","",VALUE(LEFT(B151,4))) | I151: =IF(B151="","",VALUE(MID(B151,6,2)))

Sheet Suppliers
A1: بانک تأمین‌کنندگان
A2: امتیاز کل میانگین ۵ معیار ۱ تا ۱۰ است. از همین فهرست در برگه خرید نام تأمین‌کننده انتخاب می‌شود.
A3: نام | B3: شماره تماس | C3: شهر | D3: نوع محصول | E3: قیمت شاخص (کیلو) | F3: کیفیت | G3: شرایط پرداخت | H3: زمان تحویل (روز) | I3: امتیاز قیمت | J3: امتیاز کیفیت | K3: امتیاز تحویل | L3: امتیاز ثبات | M3: امتیاز پرداخت | N3: امتیاز کل | O3: وضعیت تأیید | P3: توضیحات
A4: کشاورز بروجرد | B4: 0916-200-1111 | C4: بروجرد | D4: لوبیا چیتی | E4: 92000 | F4: عالی | G4: نقد | H4: 2 | I4: 8 | J4: 9 | K4: 9 | L4: 8 | M4: 7 | N4: =IF(A4="","",IF(COUNT(I4:M4)=0,"",AVERAGE(I4:M4))) | O4: تأیید شده | P4: تأمین‌کننده اصلی لوبیا
A5: اتحادیه نخود کوهدشت | B5: 0916-200-2222 | C5: کوهدشت | D5: نخود | E5: 68000 | F5: خوب | G5: چک ۱۰ روزه | H5: 3 | I5: 9 | J5: 8 | K5: 8 | L5: 8 | M5: 8 | N5: =IF(A5="","",IF(COUNT(I5:M5)=0,"",AVERAGE(I5:M5))) | O5: تأیید شده
A6: بازرگانی حبوبات خرم‌آباد | B6: 0916-200-3333 | C6: خرم‌آباد | D6: عدس | E6: 76000 | F6: خوب | G6: نقد | H6: 1 | I6: 7 | J6: 8 | K6: 9 | L6: 7 | M6: 7 | N6: =IF(A6="","",IF(COUNT(I6:M6)=0,"",AVERAGE(I6:M6))) | O6: تأیید شده
A7: تأمین عدس دزفول | B7: 0916-200-4444 | C7: دزفول | D7: عدس | E7: 79000 | F7: متوسط | G7: نقد | H7: 4 | I7: 6 | J7: 5 | K7: 6 | L7: 5 | M7: 6 | N7: =IF(A7="","",IF(COUNT(I7:M7)=0,"",AVERAGE(I7:M7))) | O7: در انتظار | P7: یک بار رد شده
A8: کشت و صنعت لرستان | B8: 0916-200-5555 | C8: خرم‌آباد | D8: لوبیا سفید | E8: 90000 | F8: عالی | G8: چک ۲۰ روزه | H8: 5 | I8: 7 | J8: 9 | K8: 7 | L8: 8 | M8: 9 | N8: =IF(A8="","",IF(COUNT(I8:M8)=0,"",AVERAGE(I8:M8))) | O8: تأیید شده
A9: موجودی اول دوره | B9: — | C9: پلدختر | D9: همه | E9: 0 | F9: خوب | G9: — | H9: 0 | I9: 8 | J9: 8 | K9: 8 | L9: 8 | M9: 8 | N9: =IF(A9="","",IF(COUNT(I9:M9)=0,"",AVERAGE(I9:M9))) | O9: تأیید شده | P9: ردیف سیستمی — حذف نشود
N10: =IF(A10="","",IF(COUNT(I10:M10)=0,"",AVERAGE(I10:M10)))
N11: =IF(A11="","",IF(COUNT(I11:M11)=0,"",AVERAGE(I11:M11)))
N12: =IF(A12="","",IF(COUNT(I12:M12)=0,"",AVERAGE(I12:M12)))
N13: =IF(A13="","",IF(COUNT(I13:M13)=0,"",AVERAGE(I13:M13)))
N14: =IF(A14="","",IF(COUNT(I14:M14)=0,"",AVERAGE(I14:M14)))
N15: =IF(A15="","",IF(COUNT(I15:M15)=0,"",AVERAGE(I15:M15)))
N16: =IF(A16="","",IF(COUNT(I16:M16)=0,"",AVERAGE(I16:M16)))
N17: =IF(A17="","",IF(COUNT(I17:M17)=0,"",AVERAGE(I17:M17)))
N18: =IF(A18="","",IF(COUNT(I18:M18)=0,"",AVERAGE(I18:M18)))
N19: =IF(A19="","",IF(COUNT(I19:M19)=0,"",AVERAGE(I19:M19)))
N20: =IF(A20="","",IF(COUNT(I20:M20)=0,"",AVERAGE(I20:M20)))
N21: =IF(A21="","",IF(COUNT(I21:M21)=0,"",AVERAGE(I21:M21)))
... N151: =IF(A151="","",IF(COUNT(I151:M151)=0,"",AVERAGE(I151:M151)))

Sheet Employees
A1: کارکنان
A2: تا ۲۰ نفر جا دارد. پورسانت ماه از فروش همان فروشنده در ماه جاری × نرخ پورسانت حساب می‌شود.
A3: نام | B3: سمت | C3: وظایف | D3: حقوق ثابت (تومان) | E3: نرخ پورسانت | F3: پورسانت این ماه | G3: جمع دریافتی ماه | H3: تاریخ شروع | I3: وضعیت همکاری | J3: توضیحات
A4: مدیر کارگاه | B4: مدیر/مالک | C4: خرید، فروش، مالی، تصمیم‌گیری و کنترل سیستم | D4: 18000000 | E4: 0 | F4: =IF(A4="","",SUMIFS(Sales!$L$4:$L$151,Sales!$O$4:$O$151,A4,Sales!$P$4:$P$151,تنظیمات!$B$2,Sales!$Q$4:$Q$151,تنظیمات!$D$2)*IF(E4="",0,E4)) | G4: =IF(A4="","",IF(D4="",0,D4)+F4) | H4: 1403/01/01 | I4: فعال | J4: مالک کارگاه
A5: پدر مدیر | B5: مسئول انبار | C5: کارهای سبک، کنترل انبار و کمک به تولید | D5: 8000000 | E5: 0 | F5: =IF(A5="","",SUMIFS(Sales!$L$4:$L$151,Sales!$O$4:$O$151,A5,Sales!$P$4:$P$151,تنظیمات!$B$2,Sales!$Q$4:$Q$151,تنظیمات!$D$2)*IF(E5="",0,E5)) | G5: =IF(A5="","",IF(D5="",0,D5)+F5) | H5: 1403/01/01 | I5: فعال
A6: مسئول بسته‌بندی | B6: نیروی تولید | C6: پاک‌کنی و بسته‌بندی | D6: 9000000 | E6: 0 | F6: =IF(A6="","",SUMIFS(Sales!$L$4:$L$151,Sales!$O$4:$O$151,A6,Sales!$P$4:$P$151,تنظیمات!$B$2,Sales!$Q$4:$Q$151,تنظیمات!$D$2)*IF(E6="",0,E6)) | G6: =IF(A6="","",IF(D6="",0,D6)+F6) | H6: 1404/02/15 | I6: فعال | J6: نیروی خانم
A7: ویزیتور پخش | B7: ویزیتور | C7: ویزیت، فروش و پخش با ماشین شرکت | D7: 10000000 | E7: 0.02 | F7: =IF(A7="","",SUMIFS(Sales!$L$4:$L$151,Sales!$O$4:$O$151,A7,Sales!$P$4:$P$151,تنظیمات!$B$2,Sales!$Q$4:$Q$151,تنظیمات!$D$2)*IF(E7="",0,E7)) | G7: =IF(A7="","",IF(D7="",0,D7)+F7) | H7: 1404/03/01 | I7: فعال | J7: نیروی آقا — پورسانت ۲٪ روی فروش وصول‌شده
F8: =IF(A8="","",SUMIFS(Sales!$L$4:$L$151,Sales!$O$4:$O$151,A8,Sales!$P$4:$P$151,تنظیمات!$B$2,Sales!$Q$4:$Q$151,تنظیمات!$D$2)*IF(E8="",0,E8)) | G8: =IF(A8="","",IF(D8="",0,D8)+F8)
F9: =IF(A9="","",SUMIFS(Sales!$L$4:$L$151,Sales!$O$4:$O$151,A9,Sales!$P$4:$P$151,تنظیمات!$B$2,Sales!$Q$4:$Q$151,تنظیمات!$D$2)*IF(E9="",0,E9)) | G9: =IF(A9="","",IF(D9="",0,D9)+F9)
F10: =IF(A10="","",SUMIFS(Sales!$L$4:$L$151,Sales!$O$4:$O$151,A10,Sales!$P$4:$P$151,تنظیمات!$B$2,Sales!$Q$4:$Q$151,تنظیمات!$D$2)*IF(E10="",0,E10)) | G10: =IF(A10="","",IF(D10="",0,D10)+F10)
F11: =IF(A11="","",SUMIFS(Sales!$L$4:$L$151,Sales!$O$4:$O$151,A11,Sales!$P$4:$P$151,تنظیمات!$B$2,Sales!$Q$4:$Q$151,تنظیمات!$D$2)*IF(E11="",0,E11)) | G11: =IF(A11="","",IF(D11="",0,D11)+F11)
F12: =IF(A12="","",SUMIFS(Sales!$L$4:$L$151,Sales!$O$4:$O$151,A12,Sales!$P$4:$P$151,تنظیمات!$B$2,Sales!$Q$4:$Q$151,تنظیمات!$D$2)*IF(E12="",0,E12)) | G12: =IF(A12="","",IF(D12="",0,D12)+F12)
F13: =IF(A13="","",SUMIFS(Sales!$L$4:$L$151,Sales!$O$4:$O$151,A13,Sales!$P$4:$P$151,تنظیمات!$B$2,Sales!$Q$4:$Q$151,تنظیمات!$D$2)*IF(E13="",0,E13)) | G13: =IF(A13="","",IF(D13="",0,D13)+F13)
F14: =IF(A14="","",SUMIFS(Sales!$L$4:$L$151,Sales!$O$4:$O$151,A14,Sales!$P$4:$P$151,تنظیمات!$B$2,Sales!$Q$4:$Q$151,تنظیمات!$D$2)*IF(E14="",0,E14)) | G14: =IF(A14="","",IF(D14="",0,D14)+F14)
F15: =IF(A15="","",SUMIFS(Sales!$L$4:$L$151,Sales!$O$4:$O$151,A15,Sales!$P$4:$P$151,تنظیمات!$B$2,Sales!$Q$4:$Q$151,تنظیمات!$D$2)*IF(E15="",0,E15)) | G15: =IF(A15="","",IF(D15="",0,D15)+F15)
F16: =IF(A16="","",SUMIFS(Sales!$L$4:$L$151,Sales!$O$4:$O$151,A16,Sales!$P$4:$P$151,تنظیمات!$B$2,Sales!$Q$4:$Q$151,تنظیمات!$D$2)*IF(E16="",0,E16)) | G16: =IF(A16="","",IF(D16="",0,D16)+F16)
F17: =IF(A17="","",SUMIFS(Sales!$L$4:$L$151,Sales!$O$4:$O$151,A17,Sales!$P$4:$P$151,تنظیمات!$B$2,Sales!$Q$4:$Q$151,تنظیمات!$D$2)*IF(E17="",0,E17)) | G17: =IF(A17="","",IF(D17="",0,D17)+F17)
F18: =IF(A18="","",SUMIFS(Sales!$L$4:$L$151,Sales!$O$4:$O$151,A18,Sales!$P$4:$P$151,تنظیمات!$B$2,Sales!$Q$4:$Q$151,تنظیمات!$D$2)*IF(E18="",0,E18)) | G18: =IF(A18="","",IF(D18="",0,D18)+F18)
F19: =IF(A19="","",SUMIFS(Sales!$L$4:$L$151,Sales!$O$4:$O$151,A19,Sales!$P$4:$P$151,تنظیمات!$B$2,Sales!$Q$4:$Q$151,تنظیمات!$D$2)*IF(E19="",0,E19)) | G19: =IF(A19="","",IF(D19="",0,D19)+F19)
... F23: =IF(A23="","",SUMIFS(Sales!$L$4:$L$151,Sales!$O$4:$O$151,A23,Sales!$P$4:$P$151,تنظیمات!$B$2,Sales!$Q$4:$Q$151,تنظیمات!$D$2)*IF(E23="",0,E23)) | G23: =IF(A23="","",IF(D23="",0,D23)+F23)

Sheet گزارش
A1: گزارش ماهانه محصول — معادل جدول محوری (Pivot). با تغییر ماه در تنظیمات به‌روز می‌شود.
A2: =CONCATENATE("دوره: ",تنظیمات!B2," / ","ماه ",تنظیمات!D2," — ","اگر خواستید Pivot واقعی بسازید: از جدول SalesTbl برگه Sales، Insert > PivotTable")
A4: محصول | B4: خرید تأییدشده (کیلو) | C4: میانگین قیمت تمام‌شده | D4: تولید پاک‌شده (کیلو) | E4: ضایعات (کیلو) | F4: درصد ضایعات | G4: فروش (کیلو) | H4: فروش (تومان) | I4: موجودی مواد | J4: موجودی محصول
A5: لوبیا چیتی | B5: =SUMIFS(Purchases!$E$4:$E$151,Purchases!$D$4:$D$151,A5,Purchases!$K$4:$K$151,"تأیید شده",Purchases!$M$4:$M$151,تنظیمات!$B$2,Purchases!$N$4:$N$151,تنظیمات!$D$2) | C5: =IFERROR(SUMIFS(Purchases!$G$4:$G$151,Purchases!$D$4:$D$151,A5,Purchases!$K$4:$K$151,"تأیید شده",Purchases!$M$4:$M$151,تنظیمات!$B$2,Purchases!$N$4:$N$151,تنظیمات!$D$2)/B5+SUMIFS(Purchases!$H$4:$H$151,Purchases!$D$4:$D$151,A5,Purchases!$K$4:$K$151,"تأیید شده",Purchases!$M$4:$M$151,تنظیمات!$B$2,Purchases!$N$4:$N$151,تنظیمات!$D$2)/B5,0) | D5: =SUMIFS(Production!$E$4:$E$151,Production!$C$4:$C$151,A5,Production!$M$4:$M$151,تنظیمات!$B$2,Production!$N$4:$N$151,تنظیمات!$D$2) | E5: =SUMIFS(Production!$F$4:$F$151,Production!$C$4:$C$151,A5,Production!$M$4:$M$151,تنظیمات!$B$2,Production!$N$4:$N$151,تنظیمات!$D$2) | F5: =IF(D5=0,"",E5/(D5+E5)) | G5: =SUMIFS(Sales!$H$4:$H$151,Sales!$E$4:$E$151,A5,Sales!$P$4:$P$151,تنظیمات!$B$2,Sales!$Q$4:$Q$151,تنظیمات!$D$2) | H5: =SUMIFS(Sales!$L$4:$L$151,Sales!$E$4:$E$151,A5,Sales!$P$4:$P$151,تنظیمات!$B$2,Sales!$Q$4:$Q$151,تنظیمات!$D$2) | I5: =SUMIF(Inventory!$B$5:$B$11,A5,Inventory!$C$5:$C$11) | J5: =SUMIF(Inventory!$B$14:$B$20,A5,Inventory!$C$14:$C$20)
A6: لوبیا قرمز | B6: =SUMIFS(Purchases!$E$4:$E$151,Purchases!$D$4:$D$151,A6,Purchases!$K$4:$K$151,"تأیید شده",Purchases!$M$4:$M$151,تنظیمات!$B$2,Purchases!$N$4:$N$151,تنظیمات!$D$2) | C6: =IFERROR(SUMIFS(Purchases!$G$4:$G$151,Purchases!$D$4:$D$151,A6,Purchases!$K$4:$K$151,"تأیید شده",Purchases!$M$4:$M$151,تنظیمات!$B$2,Purchases!$N$4:$N$151,تنظیمات!$D$2)/B6+SUMIFS(Purchases!$H$4:$H$151,Purchases!$D$4:$D$151,A6,Purchases!$K$4:$K$151,"تأیید شده",Purchases!$M$4:$M$151,تنظیمات!$B$2,Purchases!$N$4:$N$151,تنظیمات!$D$2)/B6,0) | D6: =SUMIFS(Production!$E$4:$E$151,Production!$C$4:$C$151,A6,Production!$M$4:$M$151,تنظیمات!$B$2,Production!$N$4:$N$151,تنظیمات!$D$2) | E6: =SUMIFS(Production!$F$4:$F$151,Production!$C$4:$C$151,A6,Production!$M$4:$M$151,تنظیمات!$B$2,Production!$N$4:$N$151,تنظیمات!$D$2) | F6: =IF(D6=0,"",E6/(D6+E6)) | G6: =SUMIFS(Sales!$H$4:$H$151,Sales!$E$4:$E$151,A6,Sales!$P$4:$P$151,تنظیمات!$B$2,Sales!$Q$4:$Q$151,تنظیمات!$D$2) | H6: =SUMIFS(Sales!$L$4:$L$151,Sales!$E$4:$E$151,A6,Sales!$P$4:$P$151,تنظیمات!$B$2,Sales!$Q$4:$Q$151,تنظیمات!$D$2) | I6: =SUMIF(Inventory!$B$5:$B$11,A6,Inventory!$C$5:$C$11) | J6: =SUMIF(Inventory!$B$14:$B$20,A6,Inventory!$C$14:$C$20)
A7: لوبیا سفید | B7: =SUMIFS(Purchases!$E$4:$E$151,Purchases!$D$4:$D$151,A7,Purchases!$K$4:$K$151,"تأیید شده",Purchases!$M$4:$M$151,تنظیمات!$B$2,Purchases!$N$4:$N$151,تنظیمات!$D$2) | C7: =IFERROR(SUMIFS(Purchases!$G$4:$G$151,Purchases!$D$4:$D$151,A7,Purchases!$K$4:$K$151,"تأیید شده",Purchases!$M$4:$M$151,تنظیمات!$B$2,Purchases!$N$4:$N$151,تنظیمات!$D$2)/B7+SUMIFS(Purchases!$H$4:$H$151,Purchases!$D$4:$D$151,A7,Purchases!$K$4:$K$151,"تأیید شده",Purchases!$M$4:$M$151,تنظیمات!$B$2,Purchases!$N$4:$N$151,تنظیمات!$D$2)/B7,0) | D7: =SUMIFS(Production!$E$4:$E$151,Production!$C$4:$C$151,A7,Production!$M$4:$M$151,تنظیمات!$B$2,Production!$N$4:$N$151,تنظیمات!$D$2) | E7: =SUMIFS(Production!$F$4:$F$151,Production!$C$4:$C$151,A7,Production!$M$4:$M$151,تنظیمات!$B$2,Production!$N$4:$N$151,تنظیمات!$D$2) | F7: =IF(D7=0,"",E7/(D7+E7)) | G7: =SUMIFS(Sales!$H$4:$H$151,Sales!$E$4:$E$151,A7,Sales!$P$4:$P$151,تنظیمات!$B$2,Sales!$Q$4:$Q$151,تنظیمات!$D$2) | H7: =SUMIFS(Sales!$L$4:$L$151,Sales!$E$4:$E$151,A7,Sales!$P$4:$P$151,تنظیمات!$B$2,Sales!$Q$4:$Q$151,تنظیمات!$D$2) | I7: =SUMIF(Inventory!$B$5:$B$11,A7,Inventory!$C$5:$C$11) | J7: =SUMIF(Inventory!$B$14:$B$20,A7,Inventory!$C$14:$C$20)
A8: عدس | B8: =SUMIFS(Purchases!$E$4:$E$151,Purchases!$D$4:$D$151,A8,Purchases!$K$4:$K$151,"تأیید شده",Purchases!$M$4:$M$151,تنظیمات!$B$2,Purchases!$N$4:$N$151,تنظیمات!$D$2) | C8: =IFERROR(SUMIFS(Purchases!$G$4:$G$151,Purchases!$D$4:$D$151,A8,Purchases!$K$4:$K$151,"تأیید شده",Purchases!$M$4:$M$151,تنظیمات!$B$2,Purchases!$N$4:$N$151,تنظیمات!$D$2)/B8+SUMIFS(Purchases!$H$4:$H$151,Purchases!$D$4:$D$151,A8,Purchases!$K$4:$K$151,"تأیید شده",Purchases!$M$4:$M$151,تنظیمات!$B$2,Purchases!$N$4:$N$151,تنظیمات!$D$2)/B8,0) | D8: =SUMIFS(Production!$E$4:$E$151,Production!$C$4:$C$151,A8,Production!$M$4:$M$151,تنظیمات!$B$2,Production!$N$4:$N$151,تنظیمات!$D$2) | E8: =SUMIFS(Production!$F$4:$F$151,Production!$C$4:$C$151,A8,Production!$M$4:$M$151,تنظیمات!$B$2,Production!$N$4:$N$151,تنظیمات!$D$2) | F8: =IF(D8=0,"",E8/(D8+E8)) | G8: =SUMIFS(Sales!$H$4:$H$151,Sales!$E$4:$E$151,A8,Sales!$P$4:$P$151,تنظیمات!$B$2,Sales!$Q$4:$Q$151,تنظیمات!$D$2) | H8: =SUMIFS(Sales!$L$4:$L$151,Sales!$E$4:$E$151,A8,Sales!$P$4:$P$151,تنظیمات!$B$2,Sales!$Q$4:$Q$151,تنظیمات!$D$2) | I8: =SUMIF(Inventory!$B$5:$B$11,A8,Inventory!$C$5:$C$11) | J8: =SUMIF(Inventory!$B$14:$B$20,A8,Inventory!$C$14:$C$20)
A9: نخود | B9: =SUMIFS(Purchases!$E$4:$E$151,Purchases!$D$4:$D$151,A9,Purchases!$K$4:$K$151,"تأیید شده",Purchases!$M$4:$M$151,تنظیمات!$B$2,Purchases!$N$4:$N$151,تنظیمات!$D$2) | C9: =IFERROR(SUMIFS(Purchases!$G$4:$G$151,Purchases!$D$4:$D$151,A9,Purchases!$K$4:$K$151,"تأیید شده",Purchases!$M$4:$M$151,تنظیمات!$B$2,Purchases!$N$4:$N$151,تنظیمات!$D$2)/B9+SUMIFS(Purchases!$H$4:$H$151,Purchases!$D$4:$D$151,A9,Purchases!$K$4:$K$151,"تأیید شده",Purchases!$M$4:$M$151,تنظیمات!$B$2,Purchases!$N$4:$N$151,تنظیمات!$D$2)/B9,0) | D9: =SUMIFS(Production!$E$4:$E$151,Production!$C$4:$C$151,A9,Production!$M$4:$M$151,تنظیمات!$B$2,Production!$N$4:$N$151,تنظیمات!$D$2) | E9: =SUMIFS(Production!$F$4:$F$151,Production!$C$4:$C$151,A9,Production!$M$4:$M$151,تنظیمات!$B$2,Production!$N$4:$N$151,تنظیمات!$D$2) | F9: =IF(D9=0,"",E9/(D9+E9)) | G9: =SUMIFS(Sales!$H$4:$H$151,Sales!$E$4:$E$151,A9,Sales!$P$4:$P$151,تنظیمات!$B$2,Sales!$Q$4:$Q$151,تنظیمات!$D$2) | H9: =SUMIFS(Sales!$L$4:$L$151,Sales!$E$4:$E$151,A9,Sales!$P$4:$P$151,تنظیمات!$B$2,Sales!$Q$4:$Q$151,تنظیمات!$D$2) | I9: =SUMIF(Inventory!$B$5:$B$11,A9,Inventory!$C$5:$C$11) | J9: =SUMIF(Inventory!$B$14:$B$20,A9,Inventory!$C$14:$C$20)
A10: لپه | B10: =SUMIFS(Purchases!$E$4:$E$151,Purchases!$D$4:$D$151,A10,Purchases!$K$4:$K$151,"تأیید شده",Purchases!$M$4:$M$151,تنظیمات!$B$2,Purchases!$N$4:$N$151,تنظیمات!$D$2) | C10: =IFERROR(SUMIFS(Purchases!$G$4:$G$151,Purchases!$D$4:$D$151,A10,Purchases!$K$4:$K$151,"تأیید شده",Purchases!$M$4:$M$151,تنظیمات!$B$2,Purchases!$N$4:$N$151,تنظیمات!$D$2)/B10+SUMIFS(Purchases!$H$4:$H$151,Purchases!$D$4:$D$151,A10,Purchases!$K$4:$K$151,"تأیید شده",Purchases!$M$4:$M$151,تنظیمات!$B$2,Purchases!$N$4:$N$151,تنظیمات!$D$2)/B10,0) | D10: =SUMIFS(Production!$E$4:$E$151,Production!$C$4:$C$151,A10,Production!$M$4:$M$151,تنظیمات!$B$2,Production!$N$4:$N$151,تنظیمات!$D$2) | E10: =SUMIFS(Production!$F$4:$F$151,Production!$C$4:$C$151,A10,Production!$M$4:$M$151,تنظیمات!$B$2,Production!$N$4:$N$151,تنظیمات!$D$2) | F10: =IF(D10=0,"",E10/(D10+E10)) | G10: =SUMIFS(Sales!$H$4:$H$151,Sales!$E$4:$E$151,A10,Sales!$P$4:$P$151,تنظیمات!$B$2,Sales!$Q$4:$Q$151,تنظیمات!$D$2) | H10: =SUMIFS(Sales!$L$4:$L$151,Sales!$E$4:$E$151,A10,Sales!$P$4:$P$151,تنظیمات!$B$2,Sales!$Q$4:$Q$151,تنظیمات!$D$2) | I10: =SUMIF(Inventory!$B$5:$B$11,A10,Inventory!$C$5:$C$11) | J10: =SUMIF(Inventory!$B$14:$B$20,A10,Inventory!$C$14:$C$20)
A11: ماش | B11: =SUMIFS(Purchases!$E$4:$E$151,Purchases!$D$4:$D$151,A11,Purchases!$K$4:$K$151,"تأیید شده",Purchases!$M$4:$M$151,تنظیمات!$B$2,Purchases!$N$4:$N$151,تنظیمات!$D$2) | C11: =IFERROR(SUMIFS(Purchases!$G$4:$G$151,Purchases!$D$4:$D$151,A11,Purchases!$K$4:$K$151,"تأیید شده",Purchases!$M$4:$M$151,تنظیمات!$B$2,Purchases!$N$4:$N$151,تنظیمات!$D$2)/B11+SUMIFS(Purchases!$H$4:$H$151,Purchases!$D$4:$D$151,A11,Purchases!$K$4:$K$151,"تأیید شده",Purchases!$M$4:$M$151,تنظیمات!$B$2,Purchases!$N$4:$N$151,تنظیمات!$D$2)/B11,0) | D11: =SUMIFS(Production!$E$4:$E$151,Production!$C$4:$C$151,A11,Production!$M$4:$M$151,تنظیمات!$B$2,Production!$N$4:$N$151,تنظیمات!$D$2) | E11: =SUMIFS(Production!$F$4:$F$151,Production!$C$4:$C$151,A11,Production!$M$4:$M$151,تنظیمات!$B$2,Production!$N$4:$N$151,تنظیمات!$D$2) | F11: =IF(D11=0,"",E11/(D11+E11)) | G11: =SUMIFS(Sales!$H$4:$H$151,Sales!$E$4:$E$151,A11,Sales!$P$4:$P$151,تنظیمات!$B$2,Sales!$Q$4:$Q$151,تنظیمات!$D$2) | H11: =SUMIFS(Sales!$L$4:$L$151,Sales!$E$4:$E$151,A11,Sales!$P$4:$P$151,تنظیمات!$B$2,Sales!$Q$4:$Q$151,تنظیمات!$D$2) | I11: =SUMIF(Inventory!$B$5:$B$11,A11,Inventory!$C$5:$C$11) | J11: =SUMIF(Inventory!$B$14:$B$20,A11,Inventory!$C$14:$C$20)
A12: جمع | B12: =SUM(B5:B11) | D12: =SUM(D5:D11) | E12: =SUM(E5:E11) | F12: =IF(D12=0,"",E12/(D12+E12)) | G12: =SUM(G5:G11) | H12: =SUM(H5:H11) | I12: =SUM(I5:I11) | J12: =SUM(J5:J11)

Sheet فرم دریافت
B1: کارگاه بسته‌بندی حبوبات | پلدختر
B2: دریافت
B3: کد فرم: F-01 | E3: تاریخ: ____ / ____ / ________
B4: فرم ۱ — دریافت مواد اولیه | مسئول: پدر مدیر / مدیر
B6: نام تأمین‌کننده
B7: شماره تماس
B8: نوع حبوبات
B9: وزن کل (کیلوگرم)
B10: کیفیت □ عالی □ خوب □ متوسط □ ضعیف
B11: ضایعات / ناخالصی (کیلو یا شرح)
B12: شماره خودرو / شرح بار
B13: ساعت ورود
B14: توضیحات
B18: نظر مسئول انبار: □ قابل قبول □ مشروط □ رد | E18: تأیید مدیر: نام: ............ امضا: ............
B21: پس از تأیید، مدیر همان روز در برگه Purchases ثبت می‌کند. یک داده، یک بار.

Sheet فرم تولید
B1: کارگاه بسته‌بندی حبوبات | پلدختر
B2: تولید
B3: کد فرم: F-02 | E3: تاریخ: ____ / ____ / ________
B4: فرم ۲ — گزارش تولید روزانه | مسئول: نیروی بسته‌بندی
B6: محصول (نوع حبوبات)
B7: مقدار ورودی به خط (کیلو)
B8: مقدار پاک‌شده (کیلو)
B9: مقدار ضایعات (کیلو)
B10: وزن هر بسته □ ۴۰۰ گرم □ ۹۰۰ گرم □ ۱۰ کیلو
B11: تعداد بسته تولیدشده
B12: نام اپراتور
B13: ساعت شروع / پایان
B14: توضیحات / مشکل خط
B17: امضای اپراتور: ........................ | E17: امضای مسئول انبار: ........................
B20: درصد ضایعات را حساب نکنید. در Excel خودکار است. این فرم را آخر وقت به مدیر بدهید.

Sheet فرم تحویل پخش
B1: کارگاه بسته‌بندی حبوبات | پلدختر
B2: تحویل پخش
B3: کد فرم: F-03 | E3: تاریخ: ____ / ____ / ________
B4: فرم ۳ — تحویل محصول به پخش | از انبار به ویزیتور
B6: نام ویزیتور
B7: مقصد / مسیر
B9: ردیف | C9: محصول | D9: وزن بسته | E9: تعداد | F9: وزن کل | G9: توضیح
B10: 1
B11: 2
B12: 3
B13: 4
B14: 5
B15: 6
B16: 7
B17: 8
B18: 9
B19: 10
B21: تحویل‌دهنده (انبار) نام: .......... امضا: .......... | E21: تحویل‌گیرنده (ویزیتور) نام: .......... امضا: ..........

Sheet فرم ویزیت
B1: کارگاه بسته‌بندی حبوبات | پلدختر
B2: ویزیت
B3: کد فرم: F-04 | E3: تاریخ: ____ / ____ / ________
B4: فرم ۴ — گزارش روزانه ویزیتور
B6: منطقه / مسیر
B7: تعداد ویزیت برنامه‌ریزی‌شده
B8: تعداد ویزیت انجام‌شده
B9: تعداد مشتریان جدید
B10: تعداد سفارش گرفته‌شده
B11: مبلغ فروش / سفارش (تومان)
B12: مبلغ وصول‌شده (تومان)
B13: کیلومتر شمار (شروع / پایان)
B14: هزینه سوخت (تومان)
B15: مشکلات مسیر / مشتری
B19: امضای ویزیتور: ........................ تأیید مدیر: ........................

Sheet فرم خروج کالا
B1: کارگاه بسته‌بندی حبوبات | پلدختر
B2: خروج کالا
B3: کد فرم: F-05 | E3: تاریخ: ____ / ____ / ________
B4: فرم ۵ — خروج کالا برای مشتری
B6: نام مشتری
B7: شهر / آدرس
B9: ردیف | C9: محصول | D9: تعداد | E9: مقدار (کیلو) | F9: مبلغ (تومان) | G9: توضیح
B10: 1
B11: 2
B12: 3
B13: 4
B14: 5
B15: 6
B16: 7
B17: 8
B19: جمع مبلغ: ........................ تومان | E19: وصول در محل: □ کامل □ بخشی □ نسیه
B21: تحویل‌دهنده نام: .......... امضا: .......... | E21: تحویل‌گیرنده (مشتری) نام: .......... امضا: ..........

Sheet فرم شمارش
B1: کارگاه بسته‌بندی حبوبات | پلدختر
B2: شمارش
B3: کد فرم: F-06 | E3: تاریخ: ____ / ____ / ________
B4: فرم ۶ — شمارش موجودی | مسئول: پدر مدیر
B6: شمارش باید با خلاصه برگه Inventory مقایسه شود. اختلاف را همان روز در دفتر تعدیل بزنید.
B8: محصول | C8: مواد/نهایی | D8: ثبت سیستم | E8: موجودی واقعی | F8: اختلاف | G8: علت اختلاف
B9: لوبیا چیتی | C9: مواد اولیه
B10: لوبیا قرمز | C10: مواد اولیه
B11: لوبیا سفید | C11: مواد اولیه
B12: عدس | C12: مواد اولیه
B13: نخود | C13: مواد اولیه
B14: لپه | C14: مواد اولیه
B15: ماش | C15: مواد اولیه
B16: لوبیا چیتی | C16: محصول نهایی
B17: لوبیا قرمز | C17: محصول نهایی
B18: لوبیا سفید | C18: محصول نهایی
B19: عدس | C19: محصول نهایی
B20: نخود | C20: محصول نهایی
... B22: ماش | C22: محصول نهایی
B24: تأیید مسئول انبار: .................. تأیید مدیر: .................. تاریخ: ____ / ____ / ________

Sheet فرم هزینه
B1: کارگاه بسته‌بندی حبوبات | پلدختر
B2: هزینه
B3: کد فرم: F-07 | E3: تاریخ: ____ / ____ / ________
B4: فرم ۷ — ثبت هزینه
B6: نوع هزینه □ حقوق □ اجاره □ برق □ گاز □ سوخت □ بسته‌بندی □ تعمیرات □ حمل □ آب □ متفرقه
B7: مبلغ (تومان) — به عدد
B8: مبلغ به حروف
B9: پرداخت‌کننده
B10: روش پرداخت □ نقد □ کارت □ چک □ نسیه
B11: شرح / بابت
B13: امضای پرداخت‌کننده: .................. تأیید مدیر: ..................

Sheet فرم ارزیابی تأمین
B1: کارگاه بسته‌بندی حبوبات | پلدختر
B2: ارزیابی تأمین
B3: کد فرم: F-08 | E3: تاریخ: ____ / ____ / ________
B4: فرم ۸ — ارزیابی تأمین‌کننده | امتیاز ۱ (ضعیف) تا ۱۰ (عالی)
B6: نام تأمین‌کننده
B7: محصول مورد ارزیابی
B8: تاریخ بار
B10: معیار | D10: امتیاز (۱–۱۰) | E10: توضیح
B11: قیمت
B12: کیفیت
B13: تحویل به‌موقع
B14: ثبات تأمین
B15: شرایط پرداخت
B17: جمع / میانگین | D17: میانگین را در برگه Suppliers وارد کنید
B19: تصمیم: □ ادامه همکاری □ تذکر □ قطع همکاری امضای مدیر: ........................

Sheet Lists
A1: محصولات | B1: وزن_بسته | C1: کیفیت | D1: وضعیت_تأیید | E1: نوع_مشتری | F1: ABC | G1: وضعیت_مشتری | H1: نوع_هزینه | I1: روش_پرداخت | J1: شهرها | K1: محل | L1: نوع_موجودی | M1: واحد | N1: سمت | O1: وضعیت_کار | P1: مناطق | Q1: ماه_نام | R1: کارکنان | S1: شماره_ماه | U1: محصول | V1: فروش_تومان | W1: تولید_کیلو
A2: لوبیا چیتی | B2: 0.4 | C2: عالی | D2: تأیید شده | E2: عمده‌فروش | F2: A | G2: فعال | H2: حقوق | I2: نقد | J2: پلدختر | K2: انبار مواد اولیه | L2: مواد اولیه | M2: کیلوگرم | N2: مدیر/مالک | O2: فعال | P2: پلدختر شهر | Q2: فروردین | R2: مدیر کارگاه | S2: 1 | U2: لوبیا چیتی | V2: =SUMIFS(Sales!$L$2:$L$151,Sales!$E$2:$E$151,U2,Sales!$P$2:$P$151,تنظیمات!$B$2,Sales!$Q$2:$Q$151,تنظیمات!$B$3) | W2: =SUMIFS(Production!$E$2:$E$151,Production!$C$2:$C$151,U2,Production!$M$2:$M$151,تنظیمات!$B$2,Production!$N$2:$N$151,تنظیمات!$B$3)
A3: لوبیا قرمز | B3: 0.9 | C3: خوب | D3: در انتظار | E3: خرده‌فروش | F3: B | G3: غیرفعال | H3: اجاره | I3: کارت | J3: خرم‌آباد | K3: سالن تولید | L3: محصول نهایی | M3: بسته | N3: مسئول انبار | O3: قطع همکاری | P3: پلدختر روستا | Q3: اردیبهشت | R3: پدر مدیر | S3: 2 | U3: لوبیا قرمز | V3: =SUMIFS(Sales!$L$2:$L$151,Sales!$E$2:$E$151,U3,Sales!$P$2:$P$151,تنظیمات!$B$2,Sales!$Q$2:$Q$151,تنظیمات!$B$3) | W3: =SUMIFS(Production!$E$2:$E$151,Production!$C$2:$C$151,U3,Production!$M$2:$M$151,تنظیمات!$B$2,Production!$N$2:$N$151,تنظیمات!$B$3)
A4: لوبیا سفید | B4: 10 | C4: متوسط | D4: رد شده | E4: سوپرمارکت | F4: C | G4: بالقوه | H4: برق | I4: چک | J4: کوهدشت | K4: انبار محصول نهایی | N4: نیروی تولید | P4: خرم‌آباد | Q4: خرداد | R4: مسئول بسته‌بندی | S4: 3 | U4: لوبیا سفید | V4: =SUMIFS(Sales!$L$2:$L$151,Sales!$E$2:$E$151,U4,Sales!$P$2:$P$151,تنظیمات!$B$2,Sales!$Q$2:$Q$151,تنظیمات!$B$3) | W4: =SUMIFS(Production!$E$2:$E$151,Production!$C$2:$C$151,U4,Production!$M$2:$M$151,تنظیمات!$B$2,Production!$N$2:$N$151,تنظیمات!$B$3)
A5: عدس | C5: ضعیف | E5: رستوران | H5: گاز | I5: نسیه | J5: رومشکان | K5: ماشین پخش | N5: ویزیتور | P5: کوهدشت | Q5: تیر | R5: ویزیتور پخش | S5: 4 | U5: عدس | V5: =SUMIFS(Sales!$L$2:$L$151,Sales!$E$2:$E$151,U5,Sales!$P$2:$P$151,تنظیمات!$B$2,Sales!$Q$2:$Q$151,تنظیمات!$B$3) | W5: =SUMIFS(Production!$E$2:$E$151,Production!$C$2:$C$151,U5,Production!$M$2:$M$151,تنظیمات!$B$2,Production!$N$2:$N$151,تنظیمات!$B$3)
A6: نخود | E6: مصرف‌کننده | H6: سوخت | J6: معمولان | N6: کمک تولید | P6: رومشکان | Q6: مرداد | S6: 5 | U6: نخود | V6: =SUMIFS(Sales!$L$2:$L$151,Sales!$E$2:$E$151,U6,Sales!$P$2:$P$151,تنظیمات!$B$2,Sales!$Q$2:$Q$151,تنظیمات!$B$3) | W6: =SUMIFS(Production!$E$2:$E$151,Production!$C$2:$C$151,U6,Production!$M$2:$M$151,تنظیمات!$B$2,Production!$N$2:$N$151,تنظیمات!$B$3)
A7: لپه | H7: بسته‌بندی | J7: اندیمشک | N7: حسابدار | P7: معمولان | Q7: شهریور | S7: 6 | U7: لپه | V7: =SUMIFS(Sales!$L$2:$L$151,Sales!$E$2:$E$151,U7,Sales!$P$2:$P$151,تنظیمات!$B$2,Sales!$Q$2:$Q$151,تنظیمات!$B$3) | W7: =SUMIFS(Production!$E$2:$E$151,Production!$C$2:$C$151,U7,Production!$M$2:$M$151,تنظیمات!$B$2,Production!$N$2:$N$151,تنظیمات!$B$3)
A8: ماش | H8: تعمیرات | J8: دزفول | Q8: مهر | S8: 7 | U8: ماش | V8: =SUMIFS(Sales!$L$2:$L$151,Sales!$E$2:$E$151,U8,Sales!$P$2:$P$151,تنظیمات!$B$2,Sales!$Q$2:$Q$151,تنظیمات!$B$3) | W8: =SUMIFS(Production!$E$2:$E$151,Production!$C$2:$C$151,U8,Production!$M$2:$M$151,تنظیمات!$B$2,Production!$N$2:$N$151,تنظیمات!$B$3)
H9: حمل | J9: بروجرد | Q9: آبان | S9: 8
H10: آب | Q10: آذر | S10: 9
H11: متفرقه | Q11: دی | S11: 10
Q12: بهمن | S12: 11
Q13: اسفند | S13: 12
